Workbook
Name CV_AIConfidence: 'Controlled Values'!$A$5:$A$7
Name CV_CandidateAssessment: 'Controlled Values'!$F$5:$F$7
Name CV_ClusterAssignmentType: 'Controlled Values'!$P$5:$P$8
Name CV_ClusterStatus: 'Controlled Values'!$I$5:$I$7
Name CV_EntityType: 'Controlled Values'!$M$5:$M$14
Name CV_EvidenceRecordType: 'Controlled Values'!$O$5:$O$6
Name CV_ExceptionSeverity: 'Controlled Values'!$J$5:$J$8
Name CV_InitiativeMappingRelationship: 'Controlled Values'!$E$5:$E$10
Name CV_InitiativeStatus: 'Controlled Values'!$H$5:$H$11
Name CV_PracticeMappingRelationship: 'Controlled Values'!$D$5:$D$9
Name CV_ProblemMappingRelationship: 'Controlled Values'!$C$5:$C$10
Name CV_RecordOrigin: 'Controlled Values'!$L$5:$L$6
Name CV_ResolutionStatus: 'Controlled Values'!$K$5:$K$8
Name CV_ReviewDecision: 'Controlled Values'!$N$5:$N$8
Name CV_ReviewStatus: 'Controlled Values'!$B$5:$B$9
Name CV_YesNo: 'Controlled Values'!$G$5:$G$6

Sheet Read Me
A1: Controlled Consolidation Working Workbook
A2: Step 0 structure for controlled consolidation; source workbooks are not modified.
A4: WORKFLOW AND REVIEW GATES
A5: 1. Import | B5: Copy every source column unchanged into Problems and Practices; add controlled metadata to the right.
A6: 2. Assess | B6: Generate candidate problems only in a later approved step, with evidence and confidence rationale.
A7: 3. Map | B7: Review candidate-to-problem, practice-to-problem, and initiative-to-problem relationships.
A8: 4. Cluster | B8: Define clusters separately from overlapping, many-to-many evidence-record assignments.
A9: 5. Review | B9: A reviewer explicitly records governing decisions in Review Log; records are not automatically approved.
A10: Imported confidence | B10: Imported Problems and Practices have blank AIConfidence and ConfidenceReason.
A11: ReviewDecisionID | B11: When retained in an entity table, this identifies the current governing review decision.
A13: CONTROL PRINCIPLES
A14: Entity IDs | B14: Imported problems use WS1-P###; practices use ESP-S###; ESP-P### remains the existing derived-problem reference. New IDs are created only for approved new problems and controlled records.
A15: Review gate | B15: Not reviewed and In review records are working records. Approval requires an explicit review decision.
A16: Decision log | B16: ReviewLog is explicitly maintained and is not an automatic audit trail; changes, versions, and timestamps are not captured automatically.
A17: ClusterStatus | B17: Describes whether a cluster definition is Draft, Active, or Retired.
A18: ReviewStatus | B18: Describes the review stage of a record: Not reviewed, In review, Needs clarification, Approved, or Rejected.
A19: Evidence discipline | B19: Owner, sponsoring unit, initiative status, and evidence date remain blank when not explicitly supported by a source.
A20: EVIDENCE RECORDS AND OVERLAPPING CLUSTER ASSIGNMENTS
A21: Evidenced problem space | B21: The evidenced problem space consists of Workshop problems and ESP-derived problem records. | C21: EPS = Existing Practices and Standards
A22: Direct assignment | B22: Both record types may be assigned directly to clusters.
A23: Multiple assignments | B23: A problem may be assigned to several clusters.
A24: Analytical lenses | B24: Clusters are overlapping analytical lenses, not mutually exclusive containers.
A25: Primary assignment | B25: A problem should normally have no more than one Primary assignment.
A26: Permitted types | B26: Secondary, Boundary and Cross-cutting assignments are permitted.
A27: Unique problems | B27: Multiple cluster assignments for one evidence record do not represent additional unique problems.
A28: Cluster counts | B28: Cluster-level problem counts must distinguish unique evidence records from assignment rows.
A29: CONTENTS
A30: Problems | B30: Imported Workshop 1 problems retain Source problem ID (WS1-P###). Approved new problems may be added later with new controlled IDs.
A31: Practices | B31: Imported practices retain Practice ID (ESP-S###) and preserve Derived problem ID (ESP-P###) as the existing ESP reference.
A32: Candidate Problems | B32: One row per proposed problem derived from evidence. Step 0 contains headings only.
A33: Problem Mappings | B33: Relates a candidate problem to an imported or approved problem using the controlled relationship list.
A34: Practice Mappings | B34: Relates an existing practice to a problem using the controlled relationship list.
A35: Initiatives | B35: One row per initiative. Evidence-based owner, unit, status, and date remain blank unless explicitly supported by a source.
A36: Initiative Mappings | B36: Links one initiative to one problem. No mappings are created in Step 0.
A37: Clusters | B37: One row per cluster definition. ClusterStatus describes lifecycle; ReviewStatus describes review progress.
A38: Cluster Assignments | B38: One row per EvidenceRecordID–ClusterID assignment. Workshop problems and ESP-derived problem records may be assigned directly to several overlapping clusters; no assignments have been created.
A39: Exceptions | B39: Records controlled data-quality issues, conflicts, omissions, and approved deviations.
A40: Review Log | B40: Explicitly maintained decision log. It is not an automatic audit trail.
A41: Controlled Values | B41: Controlled validation lists used by the workbook.

Sheet WS2_ProblemClusters
A1: CLUSTERING OF WORKSHOP 1 PROBLEMS
A4: Cluster ID | B4: Cluster Name | C4: Classification | D4: Cluster Description | E4: Sum of cross-unit problem relevance+vote for the Primary Problem Assignments, WS1-08-26 | F4: Avg cross-unit relevance per primary problem (Col H, max 21), WS1 08-26 | G4: Number of existing local practices relevant to primary problem assignments | H4: Sum of cross-unit relevance for the relevant local practices, WS-06-262 | I4: Primary Problem Assignments | J4: Secondary Problem Assignments | K4: Cross-cutting Problem Assignments | L4: Relevant ongoing initiatives 08-26 | M4: Relevant existing local Standards and Practices Q2-26 | N4: Why this is a useful or unsuitable focus area for initiative ideation | O4: Inclusion Rule | P4: Boundary Rule | Q4: Potential overlap or boundary issues requiring human review
A5: C02 | B5: Consistent and reusable project production environments | C5: Investable opportunity space | D5: Problems caused by inconsistent project setups, standards, platforms, configurations, or local working methods that make projects slow to start, difficult to transfer, and hard to reuse across countries or projects. | E5: 116 | F5: 18 | G5: 21 | H5: 336 | I5: WS1-P011 Difficult cross-country project handover; WS1-P012 Local standards hinder work sharing; WS1-P014 Confusion from multiple project platforms; WS1-P016 Misaligned setups across software vendors; WS1-P017 Fragmented project setup and infrastructure; WS1-P018 Project standards not fully implemented | J5: WS1-P006 Inconsistent data setup across tools; WS1-P015 Inefficient file exchange between vendors; WS1-P019 Coordination challenges in multidisciplinary projects | K5: WS1-P027 Consistency accross departments in terms of digital plan and focus, lack of HoD KPI's supporting improvements in the digital space | L5: PI-RTR-001 RTR Software Standardisation Exercise: Transport-wide exercise to map engineering software by service line/spearhead, identify overlaps, improve interoperability and establish an evidence-based basis for possible standardisation and rationalisation. PI-RTR-002 Unified Production Environment: Global initiative to align supported production platforms, interoperability, data governance, production knowledge and streamlined project environments, with AI and data-centric delivery as target outcomes. PI-RTR-003 Transforming Document Management: Global project to redesign document-management processes, implement a fit-for-purpose DMS and drive behavioural change and adoption across Ramboll projects. PI-RTR-006 Software processes & portal: Ramboll Tech workstream improving software-portfolio governance, employee software journeys, request workflows and production-software support flows. PI-RTR-007 Building our Project Management and Delivery department within Major Projects: Transport Major Projects initiative to build geographically distributed PMD capability supporting more reliable and harmonised delivery of large infrastructure projects. | M5: ESP-S001 ProjectWise manager governance model (Denmark); ESP-S002 ProjectWise manager guide and standards portal (Denmark); ESP-S003 ProjectWise for production - RAMDK (Denmark); ESP-S004 Managed workspace in ProjectWise (Denmark); ESP-S005 CAD project manual and transport standards portal (Denmark); ESP-S007 Client-led data management and modelling instruction model (Finland); ESP-S008 Quadri / Trimble Connect project environment (Finland); ESP-S009 Finnish configuration packages for design tools (Finland); ESP-S010 Forma pilot with discipline templates (Finland); ESP-S011 Transport software standards portal and Teams communication channels (Finland); ESP-S012 Super-user network and office roadshow support model (Finland); ESP-S013 Integrated multi-platform project environment (Norway); ESP-S017 Project SharePoint/Teams information hub (Norway); ESP-S019 CAD Configuration / Configuration Switch (Sweden); ESP-S020 Metadata and Naming + Managed Workspaces (Sweden); ESP-S022 Opt-in model via project support SharePoint page (Sweden); ESP-S023 Project Hub (SharePoint coordination layer) (Sweden); ESP-S024 Early-phase digital delivery manager involvement (UK&I); ESP-S025 Digital fit assessment (UK&I); ESP-S026 ISO 19650-aligned ProjectWise deployment model (UK&I); ESP-S027 ProjectWise build sheet and staged mobilisation checks (UK&I) | N5: Strong ideation area. The problems form a coherent conversation about making project delivery more recognisable, repeatable, transferable, and reusable while allowing justified local or project variation. It is broad enough for multiple initiative families but still tied to a clear production outcome. | O5: Include where the main problem is variation in project infrastructure, setup, standards, platform use, or implementation of standard ways of working. | P5: Exclude data naming and semantic consistency where the primary outcome is reusable data rather than repeatable project setup. Exclude general access to guidance unless the principal failure is the setup itself. | Q5: This is the broadest proposed cluster. To break down further can be considered whether project-platform coherence and standards implementation should remain together. C02 must not become a generic "all standards and software" category. WS1-P014 may overlap strongly with C04 because platform confusion can also be an interoperability problem.
A6: C06 | B6: Production knowledge, competence and adoption | C6: Cross-cutting enabler / success factor | D6: Problems where people cannot find, understand, adopt, or consistently apply the knowledge, skills, guidance, and proven working methods needed for effective digital production. | E6: 94 | F6: 16.8 | G6: 10 | H6: 110 | I6: WS1-P013 Scattered guidance and support information; WS1-P020 Limited cross-country innovation sharing; WS1-P023 Underuse of modern modelling features; WS1-P024 Uneven digital-requirements competence; WS1-P026 Delivery teams including REC lack correct skills to deliver digital outputs (models, drawings and data principally) right first time | J6: WS1-P001 Inconsistent use of AI and automation; WS1-P003 Uncoordinated citizen-developed AI tools; WS1-P011 Difficult cross-country project handover; WS1-P012 Local standards hinder work sharing; WS1-P018 Project standards not fully implemented; WS1-P021 No path from prototype to managed product; WS1-P022 Automation difficult to understand and reuse | K6: WS1-P027 Consistency accross departments in terms of digital plan and focus, lack of HoD KPI's supporting improvements in the digital space | L6: PI-RTR-001 RTR Software Standardisation Exercise: Transport-wide exercise to map engineering software by service line/spearhead, identify overlaps, improve interoperability and establish an evidence-based basis for possible standardisation and rationalisation. PI-RTR-002 Unified Production Environment: Global initiative to align supported production platforms, interoperability, data governance, production knowledge and streamlined project environments, with AI and data-centric delivery as target outcomes. PI-RTR-003 Transforming Document Management: Global project to redesign document-management processes, implement a fit-for-purpose DMS and drive behavioural change and adoption across Ramboll projects. PI-RTR-005 Script Sharing Platform rollout and scaling: Scale a live, governed environment for sharing and reusing engineering automation assets including scripts, plugins and visual-programming solutions. PI-RTR-006 Software processes & portal: Ramboll Tech workstream improving software-portfolio governance, employee software journeys, request workflows and production-software support flows. PI-RTR-007 Building our Project Management and Delivery department within Major Projects: Transport Major Projects initiative to build geographically distributed PMD capability supporting more reliable and harmonised delivery of large infrastructure projects. | M6: ESP-S002 ProjectWise manager guide and standards portal (Denmark); ESP-S005 CAD project manual and transport standards portal (Denmark); ESP-S006 Teams-based product information and support channel (Denmark); ESP-S007 Client-led data management and modelling instruction model (Finland); ESP-S011 Transport software standards portal and Teams communication channels (Finland); ESP-S012 Super-user network and office roadshow support model (Finland); ESP-S017 Project SharePoint/Teams information hub (Norway); ESP-S023 Project Hub (SharePoint coordination layer) (Sweden); ESP-S024 Early-phase digital delivery manager involvement (UK&I); ESP-S025 Digital fit assessment (UK&I) | N6: A material supporting enabler and possibly an investable opportunity in its own right. The evidence supports more than generic training: it includes onboarding, access to current guidance, practical application of modern features, cross-country knowledge transfer, and capability to deliver correctly first time. | O6: Include where the main failure is competence, discoverability of guidance, onboarding, learning, adoption, or knowledge transfer. | P6: Exclude standards or project setups where the principal problem persists even when staff know what to do. Exclude tool-product lifecycle and technical integration problems. | Q6: C06 could become too broad if every adoption or competence dependency is assigned here. Human review should preserve the distinction between a root competence problem and competence as one implementation condition for another opportunity. WS1-P020 could alternatively be Primary in C05.
A7: C01 | B7: Reliable project mobilisation and digital delivery governance | C7: Investable opportunity space | D7: Problems where digital requirements, risks, commercial provisions, delivery arrangements, leadership alignment, or multidisciplinary coordination are not established early or consistently enough to support effective project delivery. | E7: 65 | F7: 16 | G7: 8 | H7: 46 | I7: WS1-P008 Digital risks identified too late; WS1-P019 Coordination challenges in multidisciplinary projects; WS1-P025 Current commercial model acts as blocker to digital resources and innovation; WS1-P027 Consistency accross departments in terms of digital plan and focus, lack of HoD KPI's supporting improvements in the digital space | J7: WS1-P017 Fragmented project setup and infrastructure; WS1-P024 Uneven digital-requirements competence | K7: None proposed | L7: PI-RTR-002 Unified Production Environment: Global initiative to align supported production platforms, interoperability, data governance, production knowledge and streamlined project environments, with AI and data-centric delivery as target outcomes. PI-RTR-007 Building our Project Management and Delivery department within Major Projects: Transport Major Projects initiative to build geographically distributed PMD capability supporting more reliable and harmonised delivery of large infrastructure projects. | M7: ESP-S005 CAD project manual and transport standards portal (Denmark); ESP-S013 Integrated multi-platform project environment (Norway); ESP-S014 BIMbot model exchange and automation layer (Norway); ESP-S017 Project SharePoint/Teams information hub (Norway); ESP-S023 Project Hub (SharePoint coordination layer) (Sweden); ESP-S024 Early-phase digital delivery manager involvement (UK&I); ESP-S025 Digital fit assessment (UK&I); ESP-S026 ISO 19650-aligned ProjectWise deployment model (UK&I) | N7: Strong ideation area because it connects early risk identification, coordinated delivery, viable resourcing, and internal alignment. It could support several types of initiative without prescribing the Digital Delivery Manager model or another specific response. Existing digital project roles would not make WS1-P008 non-investable because adoption, timing, coverage, capacity, and effectiveness could still be explored later. | O7: Include where the main production failure occurs during tendering, mobilisation, project planning, establishment of coordinated digital delivery, or internal alignment around digital production improvement. | P7: Exclude problems whose main issue is the technical configuration of tools and environments, data semantics, or the later exchange of information. | Q7: WS1-P019 is sparsely evidenced and might instead sit in C02 if its underlying cause is primarily inconsistent environments and standards. WS1-P025 combines project funding for digital roles with recovery of investment in automation, so its boundary with C07 needs review. WS1-P027 is more consistent with C01 than C07, but it operates at departmental rather than individual-project level.
A8: C04 | B8: Efficient information exchange and tool interoperability | C8: Investable opportunity space | D8: Problems where information, files, models, or automation cannot move reliably or efficiently between tools, vendors, teams, or project contexts. | E8: 16 | F8: 15 | G8: 2 | H8: 16 | I8: WS1-P015 Inefficient file exchange between vendors | J8: WS1-P006 Inconsistent data setup across tools; WS1-P007 Inconsistent naming and data structures; WS1-P010 Weak change tracking in data-centric workflows; WS1-P014 Confusion from multiple project platforms; WS1-P016 Misaligned setups across software vendors | K8: WS1-P022 Automation difficult to understand and reuse | L8: PI-RTR-001 RTR Software Standardisation Exercise: Transport-wide exercise to map engineering software by service line/spearhead, identify overlaps, improve interoperability and establish an evidence-based basis for possible standardisation and rationalisation. PI-RTR-002 Unified Production Environment: Global initiative to align supported production platforms, interoperability, data governance, production knowledge and streamlined project environments, with AI and data-centric delivery as target outcomes. PI-RTR-003 Transforming Document Management: Global project to redesign document-management processes, implement a fit-for-purpose DMS and drive behavioural change and adoption across Ramboll projects. | M8: ESP-S013 Integrated multi-platform project environment (Norway); ESP-S014 BIMbot model exchange and automation layer (Norway) | N8: Potentially strong but currently narrow as a Primary cluster because only WS1-P015 has an unambiguous Primary fit. Its Secondary relationships show that interoperability is a meaningful ideation lens, but later evidence may support combining it with C03 or C02 rather than retaining it as a stand-alone focus area. | O8: Include where the central production loss is manual exchange, incompatible formats, inadequate exchange frequency, or inability to connect workflows across tools. | P8: Exclude inconsistent terminology or data definitions when exchange is technically possible but meaning is inconsistent. Exclude general platform proliferation where the main problem is unclear project setup rather than movement between systems. | Q8: The principal review question is whether C04 is a distinct opportunity space or a delivery mechanism within C02 and C03. Retain it separately for now because file exchange and integration can generate a different initiative conversation from standardising setups or data definitions.
A9: C05 | B9: Scalable automation and internally developed production tools (Citizen development) | C9: Investable opportunity space | D9: Problems preventing automation and internally developed tools from being created, quality-assured, shared, maintained, adapted, and scaled across projects or units. | E9: 78 | F9: 14.6 | G9: 2 | H9: 5 | I9: WS1-P001 Inconsistent use of AI and automation; WS1-P002 Barriers to scaling internally developed tools; WS1-P003 Uncoordinated citizen-developed AI tools; WS1-P021 No path from prototype to managed product; WS1-P022 Automation difficult to understand and reuse | J9: WS1-P020 Limited cross-country innovation sharing; WS1-P023 Underuse of modern modelling features | K9: S | L9: PI-RTR-004 Enabling Citizen Development: Ramboll Tech DD&P discovery and pilot initiative to determine business needs, tooling, enablement, governance and safe ways for colleagues to create lightweight automation and solutions. PI-RTR-005 Script Sharing Platform rollout and scaling: Scale a live, governed environment for sharing and reusing engineering automation assets including scripts, plugins and visual-programming solutions. PI-RTR-006 Software processes & portal: Ramboll Tech workstream improving software-portfolio governance, employee software journeys, request workflows and production-software support flows. | M9: ESP-S030 SPOT Workflow (Major Projects); ESP-S031 CODA Data Dictionary (CDD) (Major Projects) | N9: Strong ideation area. The Primary problems cover the progression from individual experimentation through quality control, publication, reuse, maintenance, and managed-product transition. This could generate materially different initiatives without limiting the discussion to AI or one product platform. | O9: Include where the main issue concerns the lifecycle, governance, reuse, quality, publication, integration, or scaling of automation and internally developed tools. | P9: Exclude broader user competence with vendor functionality. Exclude production-data foundations unless the record's primary issue is the data itself. | Q9: There is a risk of combining two related but different spaces: citizen-development governance and managed-product lifecycle. They are retained together because the evidence describes a continuous scaling problem, but later practice and initiative mapping should test whether they support separate conversations.
A10: C07 | B10: Client, regulatory and commercial conditions for digital production | C10: Hybrid, requiring review | D10: Problems where client restrictions, confidentiality, law, contractual arrangements, or commercial mechanisms constrain work sharing, AI use, resource deployment, or investment in digital production. | E10: 31 | F10: 14.5 | G10: 4 | H10: 20 | I10: WS1-P004 Confidentiality restricts work sharing with REC; WS1-P005 Client restrictions on AI and cross-border resources | J10: WS1-P008 Digital risks identified too late; WS1-P025 Current commercial model acts as blocker to digital resources and innovation | K10: None proposed | L10: N/A | M10: ESP-S007 Client-led data management and modelling instruction model (Finland); ESP-S024 Early-phase digital delivery manager involvement (UK&I); ESP-S025 Digital fit assessment (UK&I); ESP-S026 ISO 19650-aligned ProjectWise deployment model (UK&I) | N10: Mixed suitability. WS1-P004 and WS1-P005 contain genuine constraint conditions, but they may still support ideation around earlier identification, compliant delivery patterns, adaptation, or mitigation. C07 should not automatically be excluded from investment merely because the primary limiting conditions are external. | O10: Include where an external, contractual, regulatory, confidentiality, or commercial condition is the main cause of the production limitation. | P10: Exclude internal implementation, competence, governance, or organisational-alignment failures that Ramboll can act on directly. Do not assume that an external restriction makes the whole problem non-investable. | Q10: The cluster is now more internally coherent following the movement of WS1-P027 to C01. However, it remains narrow and primarily constraint-led. WS1-P025 belongs strongly in the commercial part of this cluster, but is Primary in C01 because its statement also concerns sufficient provision for digital delivery resources and investment in production improvement.
A11: C03 | B11: Structured, trustworthy and reusable production data | C11: Investable opportunity space | D11: Problems where inconsistent data definitions, naming, structures, change control, or performance information prevent reliable reuse, automation, monitoring, or decision-making. | E11: 54 | F11: 12.75 | G11: 11 | H11: 60 | I11: WS1-P006 Inconsistent data setup across tools; WS1-P007 Inconsistent naming and data structures; WS1-P009 Insufficient live project performance data; WS1-P010 Weak change tracking in data-centric workflows | J11: WS1-P015 Inefficient file exchange between vendors; WS1-P016 Misaligned setups across software vendors | K11: WS1-P001 Inconsistent use of AI and automation; WS1-P003 Uncoordinated citizen-developed AI tools | L11: PI-RTR-001 RTR Software Standardisation Exercise: Transport-wide exercise to map engineering software by service line/spearhead, identify overlaps, improve interoperability and establish an evidence-based basis for possible standardisation and rationalisation. PI-RTR-002 Unified Production Environment: Global initiative to align supported production platforms, interoperability, data governance, production knowledge and streamlined project environments, with AI and data-centric delivery as target outcomes. PI-RTR-003 Transforming Document Management: Global project to redesign document-management processes, implement a fit-for-purpose DMS and drive behavioural change and adoption across Ramboll projects. | M11: ESP-S005 CAD project manual and transport standards portal (Denmark); ESP-S007 Client-led data management and modelling instruction model (Finland); ESP-S014 BIMbot model exchange and automation layer (Norway); ESP-S015 Model Maturity Index (MMI) and property set standard (Norway); ESP-S018 Asset coding and IFC 4x3 delivery pattern (Norway); ESP-S020 Metadata and Naming + Managed Workspaces (Sweden); ESP-S026 ISO 19650-aligned ProjectWise deployment model (UK&I); ESP-S028 ProjectWise dashboards and Teams reporting (UK&I); ESP-S030 SPOT Workflow (Major Projects); ESP-S031 CODA Data Dictionary (CDD) (Major Projects); ESP-S032 BSDD testing / mapping (Major Projects) | N11: Strong ideation area because it brings together the foundations needed for data reuse, automation, reliable monitoring, and evidence-based tendering. Ideation should distinguish data semantics, data assurance, and operational performance insight rather than assuming one data platform would address all four. | O11: Include where the central production asset affected is structured data, including its semantics, consistency, traceability, or use as evidence. | P11: Exclude movement of files or models between platforms when the principal issue is exchange mechanics rather than data meaning or trust. Exclude general project standards unless they directly govern data structure or assurance. | Q11: WS1-P009 is more about management visibility than data standards and could become a separate production-insight area if later evidence shows sufficient depth. WS1-P006 overlaps C02 because "data setup" can refer both to project configuration and data structure.

Sheet Q3_Top problems
A1: Problems captured in Workshop 1, 14. August
J3: How relevant is the problem across units? | K3: Are there relevant existing local practices which can be part of the solution, and how relevant are they in total as judged to be across units?
P4: Relevance level
A5: Problem ID | B5: Clusters WS1_08-26 | C5: Primary Clusters WS2_08-26 | D5: Short title | E5: Problem statement | F5: Example or observation | G5: Value lens(es) | H5: Cross_Unit_ProblemRelevance_Count | I5: Pri signal, by voting (WS1, 8-26) | J5: Sum of unit problem relevance + vote (WS1, 8-26) | K5: Sum of unit relevance for the relevant local practices 06-26 | L5: Relevant ongoing initiatives 08-26 (AI inferred and QAd, 8-26) | M5: Relevant existing local standards and practices Q2-26 (AI inferred and QAd, 8-26) | N5: Type | O5: Top priority in | P5: NO | Q5: SE | R5: FI | S5: DK | T5: MP | U5: REC | V5: UK&I | W5: RelevantLocalPractices_Rationale (AI inferred and QAd, 8-26) | X5: Source File | Y5: Source Sheet | Z5: Record Origin | AA5: AIConfidence | AB5: ConfidenceReason | AC5: ReviewStatus | AD5: Reviewer | AE5: ReviewerComments | AF5: ReviewDecisionID | AG5: Source Type
A6: WS1-P017 | B6: Software standardization | C6: C02 Consistent and reusable project production environments | D6: Fragmented project setup and infrastructure | E6: Project teams and disciplines lack harmonised project setup and digital infrastructure when starting projects. Individuals push for different tools, standards, and ways of working, resulting in fragmented setups across projects, reduced work sharing, and an inability to harvest and reuse data from project to project. | F6: Each new project tends to reinvent its digital infrastructure and setup depending on who is involved. Even large projects across the same teams can have slightly different configurations, making cross-project reuse and standardisation difficult. | G6: Work sharing; Project write-downs | H6: 21 | I6: 2 | J6: =Problems[[#This Row],[Cross_Unit_ProblemRelevance_Count]]+Problems[[#This Row],[Pri signal, by voting (WS1, 8-26)]] -> 23 | K6: 81 | L6: PI-RTR-001 RTR Software Standardisation Exercise: Software harmonisation can reduce fragmented tool choices, but covers only part of the broader project-environment, standards, and ways-of-working problem. PI-RTR-002 Unified Production Environment: Streamlined project environments and aligned production platforms directly respond to fragmented project setup and digital infrastructure. PI-RTR-003 Transforming Document Management: A common document-management system and revised processes can standardise one important part of the project environment, but not the complete production setup. PI-RTR-007 Building our Project Management and Delivery department within Major Projects: Harmonised delivery capability can support more consistent project setup and management in major projects, but does not directly establish technical configurations or production infrastructure. | M6: ESP-S001 ProjectWise manager governance model (Denmark) ESP-S002 ProjectWise manager guide and standards portal (Denmark) ESP-S003 ProjectWise for production - RAMDK (Denmark) ESP-S004 Managed workspace in ProjectWise (Denmark) ESP-S005 CAD project manual and transport standards portal (Denmark) ESP-S008 Quadri / Trimble Connect project environment (Finland) ESP-S009 Finnish configuration packages for design tools (Finland) ESP-S010 Forma pilot with discipline templates (Finland) ESP-S013 Integrated multi-platform project environment (Norway) ESP-S019 CAD Configuration / Configuration Switch (Sweden) ESP-S020 Metadata and Naming + Managed Workspaces (Sweden) ESP-S022 Opt-in model via project support SharePoint page (Sweden) ESP-S024 Early-phase digital delivery manager involvement (UK&I) ESP-S025 Digital fit assessment (UK&I) ESP-S026 ISO 19650-aligned ProjectWise deployment model (UK&I) ESP-S027 ProjectWise build sheet and staged mobilisation checks (UK&I) | N6: Recurring | O6: MP | P6: Experienced | Q6: Experienced | R6: Experienced | S6: Experienced | T6: Experienced | U6: Experienced | V6: Experienced | W6: ESP-S001 Assigns named local responsibility for consistent project creation, access, and administration. ESP-S002 Documents the standard setup process and manager network used to establish project environments. ESP-S003 Provides repeatable project structures, permissions, external access, and project creation. ESP-S004 Delivers common tools, configurations, and templates whenever a project is opened. ESP-S005 Defines a common project-setup baseline for naming, coordinate systems, drawings, and discipline outputs. ESP-S008 Provides a structured project environment with repeatable folder, naming, and base-setup elements. ESP-S009 Gives users a packaged starting configuration for the design tools used in projects. ESP-S010 Pilots reusable discipline and client templates intended to make project creation more standardised. ESP-S013 Provides a connected multi-platform setup for complex project delivery. ESP-S019 Deploys standard CAD configurations and templates through one mechanism. ESP-S020 Standardises naming, metadata, and managed-workspace setup. ESP-S022 Gives projects a defined request route for obtaining a supported production environment. ESP-S024 Brings digital expertise into early project decisions so the project does not begin with an unsuitable setup. ESP-S025 Assesses project complexity and determines whether a managed environment and stronger digital support are required. ESP-S026 Provides a standard managed deployment with common folders, workflows, metadata, groups, and security. ESP-S027 Captures requirements, stages the environment, checks it, and approves it before production use. | X6: 2026-08 Workshop_1_problem_register.xlsx | Y6: Problem register | Z6: Imported | AC6: Not reviewed | AG6: Workshop 1 problem
A7: WS1-P026 | B7: Tool skills; Knowledge management; Commercial | C7: C06 Production knowledge, competence and adoption | D7: Delivery teams including REC lack correct skills to deliver digital outputs (models, drawings and data principally) right first time | E7: Currently project performance is impacted by the lack of skills within the business in the digital production space. This is causing a "silent drain" on projects as we're consistently spending more time and money on outputs than planned during tender without the ability to go back to clients to request additional fee due to being Ramboll error. This is impacting project performance on a large percentage of projects. | F7: Multiple projects/frequent issue. | G7: Project write-downs | H7: 21 | I7: 0 | J7: 21 | K7: 19 | L7: PI-RTR-002 Unified Production Environment: Supported platforms, production knowledge, and streamlined environments can strengthen technical delivery capability, but the initiative does not evidence competence development across all delivery teams or REC. PI-RTR-007 Building our Project Management and Delivery department within Major Projects: Explicitly builds geographically distributed project-management and delivery capability for more reliable delivery, directly addressing part of the capability gap, although not specifically competence in production tools. | M7: ESP-S006 Teams-based product information and support channel (Denmark) ESP-S011 Transport software standards portal and Teams communication channels (Finland) ESP-S012 Super-user network and office roadshow support model (Finland) ESP-S023 Project Hub (SharePoint coordination layer) (Sweden) | N7: Recurring | O7: UK&I | P7: Experienced | Q7: Experienced | R7: Experienced | S7: Experienced | T7: Experienced | U7: Experienced | V7: Experienced | W7: ESP-S006 Gives tool users access to updates, tips, known issues, and support guidance relevant to correct tool use. ESP-S011 Provides a shared source for software guidance, templates, installation instructions, and support services. ESP-S012 Provides local super-users who can explain standards, support users, and feed practical problems back to owners. ESP-S023 Supports onboarding and training in project procedures, folder structures, and production ways of working. | X7: 2026-08 Workshop_1_problem_register.xlsx | Y7: Problem register | Z7: Imported | AC7: Not reviewed | AG7: Workshop 1 problem
A8: WS1-P011 | B8: Knowledge management; Software standardization; Undocumented/unclear standards | C8: C02 Consistent and reusable project production environments | D8: Difficult cross-country project handover | E8: Sharing projects across teams, such as RFI to RNO or RNO to RDK, requires time to understand different processes, standards, software, and local practices. This can lead to rework or quality issues. | F8: An RUK team engineer working on an RFI project needed additional time to become familiar with Finland’s processes and software competencies. | G8: Work sharing | H8: 20 | I8: 2 | J8: =Problems[[#This Row],[Cross_Unit_ProblemRelevance_Count]]+Problems[[#This Row],[Pri signal, by voting (WS1, 8-26)]] -> 22 | K8: 61 | L8: PI-RTR-001 RTR Software Standardisation Exercise: Reducing variation in software portfolios and improving interoperability can remove one source of cross-country handover friction, although differences in local processes and practices remain outside its main scope. PI-RTR-002 Unified Production Environment: Shared production platforms, environments, and knowledge can make cross-country project handovers more consistent, although they do not fully resolve local working-practice differences. PI-RTR-007 Building our Project Management and Delivery department within Major Projects: Distributed project-management and delivery capability can support more reliable and harmonised delivery between geographies, particularly for large projects, but does not directly standardise software or local technical practices. | M8: ESP-S002 ProjectWise manager guide and standards portal (Denmark) ESP-S003 ProjectWise for production - RAMDK (Denmark) ESP-S004 Managed workspace in ProjectWise (Denmark) ESP-S005 CAD project manual and transport standards portal (Denmark) ESP-S008 Quadri / Trimble Connect project environment (Finland) ESP-S011 Transport software standards portal and Teams communication channels (Finland) ESP-S012 Super-user network and office roadshow support model (Finland) ESP-S013 Integrated multi-platform project environment (Norway) ESP-S017 Project SharePoint/Teams information hub (Norway) ESP-S023 Project Hub (SharePoint coordination layer) (Sweden) ESP-S026 ISO 19650-aligned ProjectWise deployment model (UK&I) | N8: Recurring | O8: REC | P8: Recognised | Q8: Experienced | R8: Experienced | S8: Experienced | T8: Experienced | U8: Experienced | V8: Experienced | W8: ESP-S002 Documents ProjectWise setup, support steps, and contacts, reducing dependence on informal local knowledge. ESP-S003 Gives project members a repeatable structure and controlled access when joining or transferring between projects. ESP-S004 Makes the same project tools, configurations, templates, and support files available to colleagues in different locations. ESP-S005 Gives incoming teams a common reference for project setup, naming, drawing production, and discipline standards. ESP-S008 Provides a shared project environment and standard base structure that supports teams working in the same project context. ESP-S011 Gives transferred staff one source for current software guidance, templates, installation information, and support. ESP-S012 Provides local people who can explain standards and route questions and feedback to responsible owners. ESP-S013 Connects the platforms used by internal and external teams and uses digital resources to bridge differences between systems. ESP-S017 Gives project members a visible entry point to the project's systems, guidance, links, and updates. ESP-S023 Provides a repeatable project-information and onboarding hub covering procedures, folder structures, and navigation. ESP-S026 Gives users and partners a familiar controlled environment through common structures, workflows, metadata, and permissions. | X8: 2026-08 Workshop_1_problem_register.xlsx | Y8: Problem register | Z8: Imported | AC8: Not reviewed | AG8: Workshop 1 problem
A9: WS1-P012 | B9: Knowledge management; Software standardization; Undocumented/unclear standards | C9: C02 Consistent and reusable project production environments | D9: Local standards hinder work sharing | E9: Work sharing between business units is difficult because units have their own poorly documented project standards. There is resistance to moving even a service line-coordinated project standard forward. | F9: At the Tampere office it was asked: ‘How can we access the data that is located in the Lahti office network drive?’ Street and landscaping have the highest resistance to change. | G9: Work sharing; Project write-downs; Tender competitiveness | H9: 20 | I9: 0 | J9: =Problems[[#This Row],[Cross_Unit_ProblemRelevance_Count]]+Problems[[#This Row],[Pri signal, by voting (WS1, 8-26)]] -> 20 | K9: 68 | L9: PI-RTR-001 RTR Software Standardisation Exercise: Supports cross-geography software harmonisation, but does not directly document or implement common project standards across business units. PI-RTR-002 Unified Production Environment: Common production knowledge and aligned environments can provide a basis for shared standards, although local resistance and incomplete documentation require additional adoption measures. PI-RTR-007 Building our Project Management and Delivery department within Major Projects: Its harmonised delivery focus and Major Projects Handbook can support more consistent delivery practices, but only partly address local technical standards and resistance to common ways of working. | M9: ESP-S002 ProjectWise manager guide and standards portal (Denmark) ESP-S003 ProjectWise for production - RAMDK (Denmark) ESP-S004 Managed workspace in ProjectWise (Denmark) ESP-S005 CAD project manual and transport standards portal (Denmark) ESP-S007 Client-led data management and modelling instruction model (Finland) ESP-S008 Quadri / Trimble Connect project environment (Finland) ESP-S011 Transport software standards portal and Teams communication channels (Finland) ESP-S012 Super-user network and office roadshow support model (Finland) ESP-S019 CAD Configuration / Configuration Switch (Sweden) ESP-S020 Metadata and Naming + Managed Workspaces (Sweden) ESP-S023 Project Hub (SharePoint coordination layer) (Sweden) ESP-S026 ISO 19650-aligned ProjectWise deployment model (UK&I) | N9: Recurring | O9: FI | P9: Recognised | Q9: Experienced | R9: Experienced | S9: Experienced | T9: Experienced | U9: Experienced | V9: Experienced | W9: ESP-S002 Makes setup guidance and responsible contacts explicit rather than leaving standards as informal local knowledge. ESP-S003 Implements a repeatable project structure and permission model across relevant projects. ESP-S004 Delivers common configurations and templates through the project environment rather than through local copies. ESP-S005 Documents common CAD and project standards in one reference point and allows projects to document only justified exceptions. ESP-S007 Translates client and agency standards into a defined project baseline for data and modelling. ESP-S008 Provides standard folder, naming, and base-setup elements within a shared project environment. ESP-S011 Provides a trusted location for current standards, templates, instructions, and support information. ESP-S012 Reinforces standards through local support, communication, feedback, and office outreach. ESP-S019 Deploys official CAD configurations and templates through a common configuration mechanism. ESP-S020 Standardises metadata, naming, and managed-workspace setup within ProjectWise. ESP-S023 Presents procedures and company practices through a repeatable project-hub structure. ESP-S026 Implements common CDE structures, metadata, workflows, and controls for participating organisations. | X9: 2026-08 Workshop_1_problem_register.xlsx | Y9: Problem register | Z9: Imported | AC9: Not reviewed | AG9: Workshop 1 problem
A10: WS1-P001 | B10: Citizen development | C10: C05 Scalable automation and internally developed production tools | D10: Inconsistent use of Enable AI and automation | E10: AI and automatization is used non-systematically among different disciplines and depends on individuals. AI tools are used by individuals and some specialist communities, but there is no common way to quality assure, share, or scale working methods. The level of maturity also varies between disciplines. | F10: Not provided. | G10: Enable AI and automation | H10: 19 | I10: 1 | J10: =Problems[[#This Row],[Cross_Unit_ProblemRelevance_Count]]+Problems[[#This Row],[Pri signal, by voting (WS1, 8-26)]] -> 20 | K10: 0 | L10: PI-RTR-004 Enabling Citizen Development: Addresses inconsistent Enable AI and automation practices by establishing common tooling, enablement, governance, and safe approaches for citizen development. PI-RTR-005 Script Sharing Platform rollout and scaling: Provides a governed environment for sharing and reusing automation assets, addressing the lack of systematic sharing and scaling, although not the full competence and quality-assurance problem. | M10: N/A | N10: Emerging | O10: NO | P10: Recognised | Q10: Experienced | R10: Experienced | S10: Experienced | T10: Experienced | U10: Recognised | V10: Experienced | W10: N/A | X10: 2026-08 Workshop_1_problem_register.xlsx | Y10: Problem register | Z10: Imported | AC10: Not reviewed | AG10: Workshop 1 problem
A11: WS1-P013 | B11: Knowledge management; Undocumented/unclear standards | C11: C06 Production knowledge, competence and adoption | D11: Scattered guidance and support information | E11: Information about ways of working, software support, education, etc. is scattered and unstructured. This makes it difficult to onboard new staff and establish standardised ways of working. | F11: Onboarding new staff is a struggle. There is no single point of entry for information. | G11: Project write-downs | H11: 19 | I11: 2 | J11: =Problems[[#This Row],[Cross_Unit_ProblemRelevance_Count]]+Problems[[#This Row],[Pri signal, by voting (WS1, 8-26)]] -> 21 | K11: 35 | L11: PI-RTR-002 Unified Production Environment: Production knowledge is part of its scope and could make guidance more consistent, although a single entry point for all support, education, and onboarding information is not explicitly evidenced. PI-RTR-003 Transforming Document Management: A fit-for-purpose document-management system and revised processes can improve the organisation of document-management guidance, but not all software, education, and working-method information. PI-RTR-006 Software processes & portal: Directly addresses employee software journeys, software requests, and production-software support flows, responding to scattered software guidance and support information. | M11: ESP-S002 ProjectWise manager guide and standards portal (Denmark) ESP-S005 CAD project manual and transport standards portal (Denmark) ESP-S006 Teams-based product information and support channel (Denmark) ESP-S011 Transport software standards portal and Teams communication channels (Finland) ESP-S012 Super-user network and office roadshow support model (Finland) ESP-S017 Project SharePoint/Teams information hub (Norway) ESP-S023 Project Hub (SharePoint coordination layer) (Sweden) | N11: Recurring | O11: SE | P11: Recognised | Q11: Experienced | R11: Experienced | S11: Experienced | T11: Experienced | U11: Recognised | V11: Experienced | W11: ESP-S002 Combines setup instructions, manager contacts, and support guidance in a common portal. ESP-S005 Provides one reference point for CAD and project setup standards. ESP-S006 Provides a visible channel for tool updates, support information, release information, and tips. ESP-S011 Provides one software-information site supported by Teams communication channels. ESP-S012 Complements written guidance with local super-users who can explain it and route feedback. ESP-S017 Gathers project links, guidance, updates, and tool information into one project entry point. ESP-S023 Gathers project procedures, navigation, communication, and onboarding information in a reusable hub. | X11: 2026-08 Workshop_1_problem_register.xlsx | Y11: Problem register | Z11: Imported | AC11: Not reviewed | AG11: Workshop 1 problem
A12: WS1-P008 | B12: Digital Delivery Management | C12: C01 Reliable project mobilisation and digital delivery governance | D12: Digital risks identified too late | E12: Digital requirements and risks are not sufficiently identified in the tender phase. There is often insufficient time to identify all risks related to digital requirements, and this is moved to the post-contract phase, resulting in underestimated work or competence needed to fulfil client requirements. This often affects project performance. | F12: Not provided. | G12: Project write-downs | H12: 18 | I12: 1 | J12: =Problems[[#This Row],[Cross_Unit_ProblemRelevance_Count]]+Problems[[#This Row],[Pri signal, by voting (WS1, 8-26)]] -> 19 | K12: 7 | L12: N/A | M12: ESP-S024 Early-phase digital delivery manager involvement (UK&I) ESP-S025 Digital fit assessment (UK&I) | N12: Recurring | O12: NO | P12: Experienced | Q12: Experienced | R12: Experienced | S12: Experienced | T12: Experienced | U12: No known relevance | V12: Experienced | W12: ESP-S024 Involves a Digital Delivery Manager during the tender gates to review digital requirements, risks, standards, and setup decisions before mobilisation. ESP-S025 Provides a structured early assessment of complexity, digital requirements, standards gaps, and delivery risks. | X12: 2026-08 Workshop_1_problem_register.xlsx | Y12: Problem register | Z12: Imported | AC12: Not reviewed | AG12: Workshop 1 problem
A13: WS1-P027 | B13: Commercial | C13: C01 Reliable project mobilisation and digital delivery governance | D13: Consistency across departments in terms of digital plan and focus, lack of HoD KPI's supporting improvements in the digital space | E13: Improving the situation in the digital management and delivery space requires all departments to push in the same direction. Historically there has been a disconnect between departments which has impacted ability to improve the situation. Moving forward there is a need for all HoD's to be involved in and understand digital needs of the business and have clear goals/KPI's associated with this. | F13: Department Plans | G13: Work sharing; Enable AI and automation; Project write-downs; Tender competitiveness | H13: 17 | I13: 0 | J13: 17 | K13: 0 | L13: PI-RTR-007 Building our Project Management and Delivery department within Major Projects: Its department-building, geographic expansion, delivery focus, and Major Projects Handbook can provide stronger common direction within Major Projects, but do not evidence aligned priorities and performance measures across all Transport departments. | M13: N/A | N13: Recurring | O13: UK&I | P13: Recognised | Q13: Experienced | R13: Recognised | S13: Experienced | T13: Recognised | U13: Recognised | V13: Experienced | W13: N/A | X13: 2026-08 Workshop_1_problem_register.xlsx | Y13: Problem register | Z13: Imported | AC13: Not reviewed | AG13: Workshop 1 problem
A14: WS1-P018 | B14: Software standardization | C14: C02 Consistent and reusable project production environments | D14: Project standards not fully implemented | E14: The project model, folder structure, and other standards are not fully implemented, resulting in diverse ways of working. | F14: Different ways of working mean longer start-up, rework, reinventing the wheel, and poorer quality. | G14: Work sharing; Enable AI and automation; Project write-downs; Tender competitiveness | H14: 17 | I14: 1 | J14: =Problems[[#This Row],[Cross_Unit_ProblemRelevance_Count]]+Problems[[#This Row],[Pri signal, by voting (WS1, 8-26)]] -> 18 | K14: 70 | L14: PI-RTR-001 RTR Software Standardisation Exercise: Can support consistent software choices, but does not directly implement project models, folder structures, templates, or standards. PI-RTR-002 Unified Production Environment: Alignment of production processes, knowledge, platforms, and environments supports practical implementation of consistent project standards and ways of working. PI-RTR-003 Transforming Document Management: Process revision, system implementation, and behavioural adoption directly support implementation of document-management standards, although not all project-production standards. PI-RTR-007 Building our Project Management and Delivery department within Major Projects: The harmonised delivery focus and Major Projects Handbook can support implementation of common delivery practices, but the documented scope does not specifically cover digital models or folder standards. | M14: ESP-S001 ProjectWise manager governance model (Denmark) ESP-S003 ProjectWise for production - RAMDK (Denmark) ESP-S004 Managed workspace in ProjectWise (Denmark) ESP-S005 CAD project manual and transport standards portal (Denmark) ESP-S008 Quadri / Trimble Connect project environment (Finland) ESP-S009 Finnish configuration packages for design tools (Finland) ESP-S010 Forma pilot with discipline templates (Finland) ESP-S011 Transport software standards portal and Teams communication channels (Finland) ESP-S012 Super-user network and office roadshow support model (Finland) ESP-S019 CAD Configuration / Configuration Switch (Sweden) ESP-S020 Metadata and Naming + Managed Workspaces (Sweden) ESP-S023 Project Hub (SharePoint coordination layer) (Sweden) ESP-S026 ISO 19650-aligned ProjectWise deployment model (UK&I) ESP-S027 ProjectWise build sheet and staged mobilisation checks (UK&I) | N14: Recurring | O14: SE | P14: Experienced | Q14: Experienced | R14: Recognised | S14: needs checking | T14: Experienced | U14: Recognised | V14: Experienced | W14: ESP-S001 Uses named managers to create projects and keep structures and access aligned with the shared standard. ESP-S003 Implements standard project structures and permission groups directly in the production environment. ESP-S004 Delivers required configurations, templates, and support files through the managed workspace. ESP-S005 Provides the documented standards projects are expected to follow and a method for recording exceptions. ESP-S008 Implements repeatable folder, naming, and base-setup elements in the project environment. ESP-S009 Deploys available templates and configurations within the design-tool setup. ESP-S010 Uses prepared discipline templates to make new project creation more consistent. ESP-S011 Makes current standards and templates discoverable and communicates updates to users. ESP-S012 Supports practical adoption through local super-users, feedback, and outreach. ESP-S019 Gives projects access to official CAD configurations and templates through a common switch. ESP-S020 Implements metadata, naming, and workspace rules in ProjectWise. ESP-S023 Presents project procedures and company practices through a repeatable project-hub template. ESP-S026 Implements standard structures, workflows, metadata, security, and review controls in the CDE. ESP-S027 Checks workflows, numbering, and environments before the production setup is approved. | X14: 2026-08 Workshop_1_problem_register.xlsx | Y14: Problem register | Z14: Imported | AC14: Not reviewed | AG14: Workshop 1 problem
A15: WS1-P020 | B15: Tool sharing | C15: C06 Production knowledge, competence and adoption | D15: Limited cross-country innovation sharing | E15: Experience sharing across countries is poor for innovative solutions that could strengthen important tenders. There are few dedicated arenas for sharing innovative solutions or ways of working across countries. | F15: Not provided. | G15: Tender competitiveness | H15: 17 | I15: 5 | J15: =Problems[[#This Row],[Cross_Unit_ProblemRelevance_Count]]+Problems[[#This Row],[Pri signal, by voting (WS1, 8-26)]] -> 22 | K15: 0 | L15: PI-RTR-002 Unified Production Environment: Shared production knowledge can improve cross-country exchange of methods and solutions, although dedicated innovation-sharing arenas and tender application are not explicit. PI-RTR-005 Script Sharing Platform rollout and scaling: Makes reusable engineering automation assets visible across teams and geographies, directly improving sharing of one important category of production innovation, although it does not cover all types of innovation or tender collaboration. | M15: N/A | N15: Recurring | O15: NO | P15: Recognised | Q15: Recognised | R15: Recognised | S15: Experienced | T15: Experienced | U15: Recognised | V15: Experienced | W15: N/A | X15: 2026-08 Workshop_1_problem_register.xlsx | Y15: Problem register | Z15: Imported | AC15: Not reviewed | AG15: Workshop 1 problem
A16: WS1-P004 | B16: Data security | C16: C07 Client, regulatory and commercial conditions for digital production | D16: Confidentiality restricts work sharing with REC | E16: Confidentiality requirements make it difficult to share work with REC. Framework agreements can restrict consultants from using REC for some projects because of the risk of data breaches. | F16: Not provided. | G16: Work sharing | H16: 17 | I16: 2 | J16: =Problems[[#This Row],[Cross_Unit_ProblemRelevance_Count]]+Problems[[#This Row],[Pri signal, by voting (WS1, 8-26)]] -> 19 | K16: 0 | L16: N/A | M16: N/A | N16: Emerging | O16: REC | P16: Recognised | Q16: Recognised | R16: Experienced | S16: needs checking | T16: Experienced | U16: Experienced | V16: Experienced | W16: N/A | X16: 2026-08 Workshop_1_problem_register.xlsx | Y16: Problem register | Z16: Imported | AC16: Not reviewed | AG16: Workshop 1 problem
A17: WS1-P019 | B17: Software standardization | C17: C01 Reliable project mobilisation and digital delivery governance | D17: Coordination challenges in multidisciplinary projects | E17: Multidisciplinary projects are difficult to manage. Coordination becomes challenging when work is shared between different business units. | F17: Not provided. | G17: Work sharing; Project write-downs | H17: 16 | I17: 0 | J17: =Problems[[#This Row],[Cross_Unit_ProblemRelevance_Count]]+Problems[[#This Row],[Pri signal, by voting (WS1, 8-26)]] -> 16 | K17: 39 | L17: PI-RTR-002 Unified Production Environment: Shared production platforms and environments can reduce digital coordination friction across disciplines and business units, although multidisciplinary management is broader than its technical scope. PI-RTR-007 Building our Project Management and Delivery department within Major Projects: Building geographically distributed project-management and delivery capability directly responds to coordination and harmonisation challenges in complex multidisciplinary projects. | M17: ESP-S005 CAD project manual and transport standards portal (Denmark) ESP-S013 Integrated multi-platform project environment (Norway) ESP-S014 BIMbot model exchange and automation layer (Norway) ESP-S017 Project SharePoint/Teams information hub (Norway) ESP-S023 Project Hub (SharePoint coordination layer) (Sweden) ESP-S024 Early-phase digital delivery manager involvement (UK&I) ESP-S026 ISO 19650-aligned ProjectWise deployment model (UK&I) | N17: Recurring | O17: REC | P17: Experienced | Q17: Experienced | R17: Recognised | S17: needs checking | T17: needs checking | U17: Experienced | V17: Experienced | W17: ESP-S005 Gives all disciplines a common project setup and output reference. ESP-S013 Connects the systems used by disciplines, clients, and contractors and uses dedicated resources to bridge them. ESP-S014 Keeps interdisciplinary models updated across platforms and reduces manual coordination exchanges. ESP-S017 Gives a multi-system project one shared navigation and information layer. ESP-S023 Provides one project communication, onboarding, and navigation layer for multidisciplinary teams. ESP-S024 Introduces digital coordination expertise while delivery arrangements are still being defined. ESP-S026 Provides controlled structures and workflows for collaboration, review, revision, and issue across organisations. | X17: 2026-08 Workshop_1_problem_register.xlsx | Y17: Problem register | Z17: Imported | AC17: Not reviewed | AG17: Workshop 1 problem
A18: WS1-P014 | B18: Platform/Software Interoperability | C18: C02 Consistent and reusable project production environments | D18: Confusion from multiple project platforms | E18: Multiple platforms create confusion in projects. All team members are affected, and project managers struggle to give clear and consistent instructions. | F18: Some activities are done in FileRy and some in the production environment. | G18: Work sharing; Enable AI and automation; Project write-downs; Tender competitiveness | H18: 16 | I18: 1 | J18: =Problems[[#This Row],[Cross_Unit_ProblemRelevance_Count]]+Problems[[#This Row],[Pri signal, by voting (WS1, 8-26)]] -> 17 | K18: 25 | L18: PI-RTR-001 RTR Software Standardisation Exercise: Identifying software overlaps and rationalisation opportunities can reduce platform proliferation, although it does not define a single project-platform model. PI-RTR-002 Unified Production Environment: Its objective of aligning supported production platforms and streamlining project environments directly responds to confusion created by multiple platforms. PI-RTR-003 Transforming Document Management: Establishing a fit-for-purpose document-management system can reduce ambiguity concerning document-management platforms, but not the wider project-platform landscape. PI-RTR-006 Software processes & portal: Better software-portfolio governance and employee software journeys can clarify which software and services should be used, although this is not full platform consolidation. | M18: ESP-S013 Integrated multi-platform project environment (Norway) ESP-S017 Project SharePoint/Teams information hub (Norway) ESP-S023 Project Hub (SharePoint coordination layer) (Sweden) ESP-S024 Early-phase digital delivery manager involvement (UK&I) ESP-S025 Digital fit assessment (UK&I) | N18: Recurring | O18: SE | P18: Recognised | Q18: Experienced | R18: Experienced | S18: Experienced | T18: Recognised | U18: No known relevance | V18: Experienced | W18: ESP-S013 Provides an operating model for connecting and coordinating several production and collaboration platforms in complex projects. ESP-S017 Gives users one navigation point across a complicated multi-system project setup. ESP-S023 Gives participants one consistent place for project navigation, procedures, and live information. ESP-S024 Supports early decisions about the appropriate CDE, tools, standards, and digital setup. ESP-S025 Provides a structured decision on whether a managed environment is needed and which digital gaps must be addressed. | X18: 2026-08 Workshop_1_problem_register.xlsx | Y18: Problem register | Z18: Imported | AC18: Not reviewed | AG18: Workshop 1 problem
A19: WS1-P015 | B19: Platform/Software Interoperability | C19: C04 Efficient information exchange and tool interoperability | D19: Inefficient file exchange between vendors | E19: Dynamic file sharing between vendors is a constant challenge. It can be labour-intensive, and the exchange frequency is often inadequate unless automated. This can cause misaligned design and time spent updating material. There is no clear process or agreement on formats used between software or on which files are the original/native design files. | F19: Not provided. | G19: Work sharing; Enable AI and automation; Project write-downs; Tender competitiveness | H19: 15 | I19: 1 | J19: =Problems[[#This Row],[Cross_Unit_ProblemRelevance_Count]]+Problems[[#This Row],[Pri signal, by voting (WS1, 8-26)]] -> 16 | K19: 16 | L19: PI-RTR-001 RTR Software Standardisation Exercise: Improved interoperability and software standardisation can reduce cross-vendor exchange friction, but the initiative does not establish file-exchange agreements, native-file rules, or automated exchange processes. PI-RTR-002 Unified Production Environment: Interoperability and streamlined production environments directly respond to recurring exchange problems between vendor ecosystems, although detailed format and native-file rules remain necessary. PI-RTR-003 Transforming Document Management: Revised document-management processes can improve control of exchanged files and documents, but do not resolve full design-tool interoperability. | M19: ESP-S013 Integrated multi-platform project environment (Norway) ESP-S014 BIMbot model exchange and automation layer (Norway) | N19: Recurring | O19: DK | P19: needs checking | Q19: Experienced | R19: Recognised | S19: Experienced | T19: Experienced | U19: No known relevance | V19: Experienced | W19: ESP-S013 Connects design tools, common data environments, and collaboration platforms through an integrated project operating model. ESP-S014 Directly automates file and model movement between platforms and can extract, merge, split, and check IFC information. | X19: 2026-08 Workshop_1_problem_register.xlsx | Y19: Problem register | Z19: Imported | AC19: Not reviewed | AG19: Workshop 1 problem
A20: WS1-P002 | B20: Citizen development | C20: C05 Scalable automation and internally developed production tools | D20: Barriers to scaling internally developed tools | E20: Internal tool development is limited by recurring factors: there is no clear way to standardise and publish a tool developed for one project, so tools are often forgotten; and the use of AI to script solutions is limited because available AI tools are not permitted for this purpose, even though scripting is performed on project material. | F20: A tool for dynamic implementation of classification is limited by the credits and tools available for AI, as well as the absence of a way to publish it in an online database. | G20: Enable AI and automation; Project write-downs; Tender competitiveness | H20: 15 | I20: 1 | J20: =Problems[[#This Row],[Cross_Unit_ProblemRelevance_Count]]+Problems[[#This Row],[Pri signal, by voting (WS1, 8-26)]] -> 16 | K20: 0 | L20: PI-RTR-004 Enabling Citizen Development: Its discovery, tooling, enablement, and pilot work can reduce barriers to developing supported internal solutions, although it does not evidence a complete publishing and product-management pathway. PI-RTR-005 Script Sharing Platform rollout and scaling: Directly provides a governed way to publish, discover, reuse, and scale internally developed scripts, plugins, and visual-programming solutions. PI-RTR-006 Software processes & portal: Improved software governance, employee journeys, and request workflows may support access to approved tooling, but only partly address publication and scaling of internally developed tools. | M20: N/A | N20: Recurring | O20: DK | P20: Recognised | Q20: Recognised | R20: Recognised | S20: Experienced | T20: Experienced | U20: No known relevance | V20: Experienced | W20: N/A | X20: 2026-08 Workshop_1_problem_register.xlsx | Y20: Problem register | Z20: Imported | AC20: Not reviewed | AG20: Workshop 1 problem
A21: WS1-P016 | B21: Software standardization | C21: C02 Consistent and reusable project production environments | D21: Misaligned setups across software vendors | E21: Projects using multiple software vendors often lack standard setups, and setups are not aligned between software. Significant project time is spent trying to ensure alignment, and delivered material may not be coherent across disciplines or meet client requirements. | F21: Title blocks are not consistent across Bentley, Tekla, and Autodesk. | G21: Work sharing; Project write-downs | H21: 14 | I21: 2 | J21: =Problems[[#This Row],[Cross_Unit_ProblemRelevance_Count]]+Problems[[#This Row],[Pri signal, by voting (WS1, 8-26)]] -> 16 | K21: 31 | L21: PI-RTR-001 RTR Software Standardisation Exercise: Directly analyses software overlaps and interoperability as a basis for standardisation, responding to inconsistent and misaligned multi-vendor setups. PI-RTR-002 Unified Production Environment: Aligning supported production platforms and interoperability directly addresses standard setups that are not aligned between software vendors. | M21: ESP-S004 Managed workspace in ProjectWise (Denmark) ESP-S009 Finnish configuration packages for design tools (Finland) ESP-S013 Integrated multi-platform project environment (Norway) ESP-S019 CAD Configuration / Configuration Switch (Sweden) ESP-S020 Metadata and Naming + Managed Workspaces (Sweden) | N21: Recurring | O21: DK | P21: Recognised | Q21: Recognised | R21: Recognised | S21: Experienced | T21: Recognised | U21: No known relevance | V21: Experienced | W21: ESP-S004 Distributes common tool configurations, menus, templates, and support files through a managed workspace. ESP-S009 Packages configurations, templates, naming, drawings, client definitions, and support files into design-tool setups. ESP-S013 Provides a connected operating setup across several vendors and platforms, supported by resources that bridge system differences. ESP-S019 Provides a common mechanism for deploying and accessing official CAD configurations and templates. ESP-S020 Aligns naming, metadata, and managed-workspace setup within the ProjectWise environment. | X21: 2026-08 Workshop_1_problem_register.xlsx | Y21: Problem register | Z21: Imported | AC21: Not reviewed | AG21: Workshop 1 problem
A22: WS1-P006 | B22: Data Strategy | C22: C03 Structured, trustworthy and reusable production data | D22: Inconsistent data setup across tools | E22: Working with project data across multiple software vendors and standards is difficult because data setups differ across software. Coding must be dynamically updated and shared live between teams and software to ensure consistent and correct implementation. The issue is increasingly important as clients request more information. | F22: On the CRNHE metro project, a whitelist database was developed to mitigate the issue, but currently available tools and options limit the solution that can be implemented. | G22: Work sharing; Enable AI and automation; Project write-downs; Tender competitiveness | H22: 14 | I22: 1 | J22: =Problems[[#This Row],[Cross_Unit_ProblemRelevance_Count]]+Problems[[#This Row],[Pri signal, by voting (WS1, 8-26)]] -> 15 | K22: 19 | L22: PI-RTR-001 RTR Software Standardisation Exercise: Its analysis of software overlaps and interoperability can address part of the inconsistent cross-tool setup, but not the full requirement for dynamically controlled and synchronised project data. PI-RTR-002 Unified Production Environment: Directly targets supported production platforms, interoperability, and data governance, responding to inconsistent data setup across tools. | M22: ESP-S014 BIMbot model exchange and automation layer (Norway) ESP-S018 Asset coding and IFC 4x3 delivery pattern (Norway) ESP-S030 SPOT Workflow (Major Projects) ESP-S031 CODA Data Dictionary (CDD) (Major Projects) ESP-S032 BSDD testing / mapping (Major Projects) | N22: Recurring, soon to be emerging | O22: DK | P22: Recognised | Q22: Experienced | R22: needs checking | S22: Experienced | T22: Recognised | U22: No known relevance | V22: Experienced | W22: ESP-S014 Automates movement and checking of model data between platforms, reducing manual cross-tool handling. ESP-S018 Applies structured asset codes and IFC properties to improve consistency in model-based data delivery. ESP-S030 Uses a shared data backbone and common data model to support parallel workflows across multiple design and analysis tools. ESP-S031 Provides common attribute definitions, types, and allowed values across projects, tools, and scripts. ESP-S032 Maps the project data dictionary to bSDD and IFC 4.3 to support standardised exchange between systems. | X22: 2026-08 Workshop_1_problem_register.xlsx | Y22: Problem register | Z22: Imported | AC22: Not reviewed | AG22: Workshop 1 problem
A23: WS1-P007 | B23: Data Strategy | C23: C03 Structured, trustworthy and reusable production data | D23: Inconsistent naming and data structures | E23: Project teams working across disciplines and tools experience inconsistent naming conventions and the absence of a unified data strategy when creating and exchanging objects across BIM models, calculation sheets, and other tools. This results in poor interoperability, fragmented workflows, and an inability to harvest and reuse data across projects. | F23: The same object is often named differently across BIM models, calculation sheets, other tools, and projects. Without shared naming conventions or a data strategy, harmonising workflows and aggregating data across projects becomes extremely difficult. | G23: Work sharing; Enable AI and automation; Project write-downs | H23: 14 | I23: 1 | J23: =Problems[[#This Row],[Cross_Unit_ProblemRelevance_Count]]+Problems[[#This Row],[Pri signal, by voting (WS1, 8-26)]] -> 15 | K23: 33 | L23: PI-RTR-001 RTR Software Standardisation Exercise: Software standardisation and interoperability analysis can reduce differences between tool conventions, but do not by themselves establish a unified naming and data strategy. PI-RTR-002 Unified Production Environment: Its data-governance and interoperability scope directly addresses fragmented data structures and poor reuse across production tools. | M23: ESP-S005 CAD project manual and transport standards portal (Denmark) ESP-S007 Client-led data management and modelling instruction model (Finland) ESP-S015 Model Maturity Index (MMI) and property set standard (Norway) ESP-S018 Asset coding and IFC 4x3 delivery pattern (Norway) ESP-S020 Metadata and Naming + Managed Workspaces (Sweden) ESP-S031 CODA Data Dictionary (CDD) (Major Projects) ESP-S032 BSDD testing / mapping (Major Projects) | N23: Recurring | O23: MP | P23: Recognised | Q23: Recognised | R23: Recognised | S23: Recognised | T23: Experienced | U23: No known relevance | V23: Experienced | W23: ESP-S005 Provides common project guidance covering naming, coordinate systems, drawing setup, and discipline outputs. ESP-S007 Establishes a project baseline for naming, data structure, deliverables, and modelling expectations. ESP-S015 Defines common model-maturity information and structured property sets across disciplines. ESP-S018 Standardises object coding and information properties for model-based asset delivery. ESP-S020 Explicitly standardises metadata, naming conventions, and managed-workspace setup. ESP-S031 Provides a single reference for attribute names, definitions, types, and permitted values. ESP-S032 Aligns the CODA dictionary with recognised bSDD and IFC 4.3 structures. | X23: 2026-08 Workshop_1_problem_register.xlsx | Y23: Problem register | Z23: Imported | AC23: Not reviewed | AG23: Workshop 1 problem
A24: WS1-P003 | B24: Citizen development | C24: C05 Scalable automation and internally developed production tools | D24: Uncoordinated citizen-developed AI tools | E24: Citizen developers and teams across the organisation use a fragmented and uncoordinated approach to building tools with AI, such as Copilot. Solutions are developed individually without shared standards, quality control, or integration with legacy systems, resulting in duplicated, low-quality, and incompatible tools that are difficult to share, integrate, and maintain. | F24: Because AI dramatically lowers development time, many citizen developers build their own tools in parallel, often solving the same problem multiple times in slightly different ways. These tools rarely connect, are not always quality-assured, and frequently clash with existing legacy tools. | G24: Work sharing; Enable AI and automation; Project write-downs | H24: 14 | I24: 1 | J24: =Problems[[#This Row],[Cross_Unit_ProblemRelevance_Count]]+Problems[[#This Row],[Pri signal, by voting (WS1, 8-26)]] -> 15 | K24: 0 | L24: PI-RTR-004 Enabling Citizen Development: Directly addresses fragmented citizen development through common enablement, governance, tooling, and safe supported approaches. PI-RTR-005 Script Sharing Platform rollout and scaling: A shared governed platform can reduce duplicated and disconnected automation development by making reusable assets visible and available across teams, although it does not by itself resolve legacy-system integration. | M24: N/A | N24: Recurring; Emerging | O24: MP | P24: Recognised | Q24: needs checking | R24: Experienced | S24: Recognised | T24: Experienced | U24: No known relevance | V24: Experienced | W24: N/A | X24: 2026-08 Workshop_1_problem_register.xlsx | Y24: Problem register | Z24: Imported | AC24: Not reviewed | AG24: Workshop 1 problem
A25: WS1-P022 | B25: Tool sharing | C25: C05 Scalable automation and internally developed production tools | D25: Automation difficult to understand and reuse | E25: It is difficult to understand or reuse automation created by another team. Automation also requires modification for specific projects or countries, and other team members may struggle to modify it. | F25: Not provided. | G25: Work sharing; Enable AI and automation | H25: 14 | I25: 0 | J25: =Problems[[#This Row],[Cross_Unit_ProblemRelevance_Count]]+Problems[[#This Row],[Pri signal, by voting (WS1, 8-26)]] -> 14 | K25: 5 | L25: PI-RTR-004 Enabling Citizen Development: Common enablement and governance can make citizen-developed solutions more reusable and understandable, although localisation and reusable documentation mechanisms are not explicit. PI-RTR-005 Script Sharing Platform rollout and scaling: Directly addresses difficulty finding and reusing internally developed automation assets by providing a governed sharing platform, although adaptation to different country contexts remains outside the documented scope. | M25: ESP-S030 SPOT Workflow (Major Projects) ESP-S031 CODA Data Dictionary (CDD) (Major Projects) | N25: Recurring | O25: REC | P25: Experienced | Q25: Recognised | R25: Recognised | S25: Recognised | T25: No known relevance | U25: Experienced | V25: Recognised | W25: ESP-S030 Uses documented building blocks, templates, workflows, toolkits, and a common data model to support reuse across connected engineering workflows. ESP-S031 Standardises attribute names and values so scripts and automation can operate consistently and be reused across CODA-aligned projects. | X25: 2026-08 Workshop_1_problem_register.xlsx | Y25: Problem register | Z25: Imported | AC25: Not reviewed | AG25: Workshop 1 problem
A26: WS1-P023 | B26: Tool skills; Knowledge management | C26: C06 Production knowledge, competence and adoption | D26: Underuse of modern modelling features | E26: Transport designers underuse new modelling and drawing features and develop workarounds for problems already solved by vendors, or need entirely new approaches. CAD and Novapoint are used as they were in 2015. Designers manually perform tasks already automated and create models in a hard way, causing quality issues and time concerns. | F26: A rail unit reported that eliminating all model- and drawing-production-related claims and budget overruns could have a major profitability impact. One business unit developed a Lisp routine to complete a task that is already a Civil 3D feature. | G26: Enable AI and automation; Tender competitiveness | H26: 14 | I26: 3 | J26: =Problems[[#This Row],[Cross_Unit_ProblemRelevance_Count]]+Problems[[#This Row],[Pri signal, by voting (WS1, 8-26)]] -> 17 | K26: 15 | L26: PI-RTR-001 RTR Software Standardisation Exercise: May identify redundant tools and standard vendor capabilities that are currently underused, but does not directly provide training or drive user adoption of modern features. PI-RTR-006 Software processes & portal: Improved production-software support flows and employee software journeys can help users access current capabilities and support, but feature-specific competence development is not explicitly evidenced. | M26: ESP-S006 Teams-based product information and support channel (Denmark) ESP-S011 Transport software standards portal and Teams communication channels (Finland) ESP-S012 Super-user network and office roadshow support model (Finland) | N26: Recurring | O26: FI | P26: Recognised | Q26: Experienced | R26: Experienced | S26: needs checking | T26: Recognised | U26: No known relevance | V26: Experienced | W26: ESP-S006 Publishes tool tips, release information, product issues, and support guidance that can expose users to available functionality. ESP-S011 Provides current software guidance, installation information, templates, and support routes through a shared portal and channels. ESP-S012 Uses super-users and office outreach to explain expected ways of working, gather user needs, and reinforce practical adoption. | X26: 2026-08 Workshop_1_problem_register.xlsx | Y26: Problem register | Z26: Imported | AC26: Not reviewed | AG26: Workshop 1 problem
A27: WS1-P025 | B27: Commercial | C27: C01 Reliable project mobilisation and digital delivery governance | D27: Current commercial model acts as blocker to digital resources and innovation | E27: Due to lack of understanding clients often challenge hours required to discharge Digital Delivery Management or Digital Coordinator roles leaving insufficient budget. Additionally AI/automation solutions are often an investment of Ramboll without a mechanism (such as value-based pricing) to get this investment back meaning impact of business performance is large and will grow as AI/automation become more and more the norm. | F27: Multiple projects/frequent issue. | G27: Enable AI and automation; Project write-downs; Tender competitiveness | H27: 13 | I27: 0 | J27: 13 | K27: 0 | L27: PI-RTR-007 Building our Project Management and Delivery department within Major Projects: Building a recognised delivery department may improve the organisational visibility and resourcing of specialist delivery roles, but the documented initiative does not establish changes to pricing or commercial models for digital roles and innovation. | M27: N/A | N27: Recurring | O27: UK&I | P27: needs checking | Q27: Experienced | R27: needs checking | S27: Recognised | T27: Recognised | U27: needs checking | V27: Experienced | W27: N/A | X27: 2026-08 Workshop_1_problem_register.xlsx | Y27: Problem register | Z27: Imported | AC27: Not reviewed | AG27: Workshop 1 problem
A28: WS1-P010 | B28: Knowledge management | C28: C03 Structured, trustworthy and reusable production data | D28: Weak change tracking in data-centric workflows | E28: Project teams managing data-centric workflows lack rigorous change tracking, validation, and change management when handling design data, requirements, and deliverables across multiple parties and tools. This results in chaotic updates, unvalidated changes propagating through projects, and reduced confidence in data quality and deliverables. | F28: Basic procedures exist for tracking changes to drawings and BIM models, but the process remains chaotic and lacks granularity. There is no rigorous way to track how data evolves, how changes are validated, or how changes are communicated to relevant parties, especially for design data, requirements, and attributes. | G28: Enable AI and automation; Project write-downs; Tender competitiveness | H28: 13 | I28: 0 | J28: =Problems[[#This Row],[Cross_Unit_ProblemRelevance_Count]]+Problems[[#This Row],[Pri signal, by voting (WS1, 8-26)]] -> 13 | K28: 8 | L28: PI-RTR-002 Unified Production Environment: Data governance and data-centric delivery support more controlled handling of project data, but the documented scope does not establish detailed change tracking, validation, and communication controls. PI-RTR-003 Transforming Document Management: Redesigning document-management processes and implementing a fit-for-purpose document-management system directly address controlled revision and management of document-based changes, although not necessarily all data-centric changes across engineering tools. | M28: ESP-S026 ISO 19650-aligned ProjectWise deployment model (UK&I) ESP-S028 ProjectWise dashboards and Teams reporting (UK&I) ESP-S030 SPOT Workflow (Major Projects) | N28: Recurring | O28: MP | P28: Recognised | Q28: needs checking | R28: Experienced | S28: needs checking | T28: Experienced | U28: No known relevance | V28: Experienced | W28: ESP-S026 Applies controlled workflows for revision, review, and issue of deliverables within a managed environment. ESP-S028 Exposes audit-trail, workflow, and file-activity information so project teams can identify changes and issues. ESP-S030 Provides a shared data backbone with data modelling, quality assurance, standardised building blocks, and automated validation. | X28: 2026-08 Workshop_1_problem_register.xlsx | Y28: Problem register | Z28: Imported | AC28: Not reviewed | AG28: Workshop 1 problem
A29: WS1-P024 | B29: Tool skills; Knowledge management | C29: C06 Production knowledge, competence and adoption | D29: Uneven digital-requirements competence | E29: Knowledge and competence related to digital requirements vary across disciplines and countries in Norwegian projects. Some disciplines are not always familiar with required formats, information content, or tools used for collaboration. | F29: Not provided. | G29: Work sharing; Project write-downs | H29: 13 | I29: 0 | J29: =Problems[[#This Row],[Cross_Unit_ProblemRelevance_Count]]+Problems[[#This Row],[Pri signal, by voting (WS1, 8-26)]] -> 13 | K29: 41 | L29: PI-RTR-002 Unified Production Environment: Shared production knowledge and aligned platforms can reduce variation in digital-delivery competence, but a targeted competence programme for digital requirements is not explicitly evidenced. PI-RTR-007 Building our Project Management and Delivery department within Major Projects: Building geographically distributed delivery capability can strengthen competence for reliable project delivery, but only partly addresses knowledge of digital formats, requirements, and collaboration tools. | M29: ESP-S005 CAD project manual and transport standards portal (Denmark) ESP-S007 Client-led data management and modelling instruction model (Finland) ESP-S011 Transport software standards portal and Teams communication channels (Finland) ESP-S012 Super-user network and office roadshow support model (Finland) ESP-S017 Project SharePoint/Teams information hub (Norway) ESP-S023 Project Hub (SharePoint coordination layer) (Sweden) ESP-S024 Early-phase digital delivery manager involvement (UK&I) ESP-S025 Digital fit assessment (UK&I) | N29: Recurring | O29: NO | P29: No known relevance | Q29: needs checking | R29: Experienced | S29: Recognised | T29: Experienced | U29: Recognised | V29: Recognised | W29: ESP-S005 Makes required project setup, naming, formats, and discipline-output guidance available through one standards reference. ESP-S007 Turns client modelling and data requirements into a documented project baseline that delivery teams can follow. ESP-S011 Provides one place for current software, template, installation, and support guidance. ESP-S012 Provides experienced local contacts who can explain standards and route questions to the relevant owners. ESP-S017 Gives project members one entry point to project guidance, updates, systems, and digital-tool information. ESP-S023 Supports onboarding and training in project procedures, folder structures, and ways of working. ESP-S024 Brings digital-delivery expertise into the project when client requirements and setup decisions are being interpreted. ESP-S025 Structures the assessment of digital context, complexity, standards gaps, and support needs. | X29: 2026-08 Workshop_1_problem_register.xlsx | Y29: Problem register | Z29: Imported | AC29: Not reviewed | AG29: Workshop 1 problem
A30: WS1-P005 | B30: Data security | C30: C07 Client, regulatory and commercial conditions for digital production | D30: Client restrictions on AI and cross-border resources | E30: Clients restrict the use of AI and resources outside Finland because infrastructure data is considered critical and its use is defined by law. Much infrastructure data is confidential, restricting the use of REC and AI. Challenging design tasks therefore need to be completed by highly skilled Finnish staff. | F30: Not provided. | G30: Work sharing; Enable AI and automation; Project write-downs; Tender competitiveness | H30: 12 | I30: 0 | J30: =Problems[[#This Row],[Cross_Unit_ProblemRelevance_Count]]+Problems[[#This Row],[Pri signal, by voting (WS1, 8-26)]] -> 12 | K30: 20 | L30: N/A | M30: ESP-S007 Client-led data management and modelling instruction model (Finland) ESP-S024 Early-phase digital delivery manager involvement (UK&I) ESP-S025 Digital fit assessment (UK&I) ESP-S026 ISO 19650-aligned ProjectWise deployment model (UK&I) | N30: Recurring | O30: FI | P30: No known relevance | Q30: Experienced | R30: Experienced | S30: needs checking | T30: Experienced | U30: No known relevance | V30: Recognised | W30: ESP-S007 Translates client, agency, system, and legal requirements into documented project data-management and modelling instructions. ESP-S024 Brings digital expertise into tender review so client restrictions and digital requirements can be identified before mobilisation. ESP-S025 Assesses the project's digital context, risks, standards gaps, and managed-environment needs before mobilisation. ESP-S026 Provides controlled security and collaboration arrangements, including support for local compliance and data-location requirements. | X30: 2026-08 Workshop_1_problem_register.xlsx | Y30: Problem register | Z30: Imported | AC30: Not reviewed | AG30: Workshop 1 problem
A31: WS1-P021 | B31: Tool sharing | C31: C05 Scalable automation and internally developed production tools | D31: No path from prototype to managed product | E31: Citizen developers and teams that could benefit from their tools lack infrastructure and support to transition tools from idea or minimum viable product into properly documented, quality-assured, maintained, and owned products. When a project ends, developers have no time, mandate, or pathway to hand over tools, resulting in valuable tools being abandoned, stuck with reluctant owners, or never scaled beyond the original project. | F31: Citizen developers often build useful tools during projects, but once the project closes there is no time or structured process to document, quality-assure, release, and transfer ownership. Developers are reluctant to remain long-term owners because maintenance, tool responsibility, host patching, and bug fixing may fall outside their remit. | G31: Work sharing; Enable AI and automation; Project write-downs | H31: 11 | I31: 2 | J31: =Problems[[#This Row],[Cross_Unit_ProblemRelevance_Count]]+Problems[[#This Row],[Pri signal, by voting (WS1, 8-26)]] -> 13 | K31: 0 | L31: PI-RTR-004 Enabling Citizen Development: Supported tooling, governance, and pilots can help citizen-developed solutions progress beyond individual experimentation, although a complete managed-product handover and ownership model is not evidenced. PI-RTR-005 Script Sharing Platform rollout and scaling: Provides a live governed environment through which automation assets can be shared, reused, and scaled beyond their originating project, although full lifecycle ownership and maintenance are not explicitly evidenced. PI-RTR-006 Software processes & portal: Governance and request workflows may support the transition of tools into managed services, but the documented scope does not establish a full prototype-to-product lifecycle. | M31: N/A | N31: Recurring; Emerging | O31: MP | P31: needs checking | Q31: needs checking | R31: needs checking | S31: Experienced | T31: Experienced | U31: No known relevance | V31: Recognised | W31: N/A | X31: 2026-08 Workshop_1_problem_register.xlsx | Y31: Problem register | Z31: Imported | AC31: Not reviewed | AG31: Workshop 1 problem
A32: WS1-P009 | B32: Knowledge management | C32: C03 Structured, trustworthy and reusable production data | D32: Insufficient live project performance data | E32: Project managers, delivery teams, and tender teams lack structured key performance indicators directly connected to real project data generated during execution. This limits their ability to monitor efficiency, budget consumption, completeness, and performance in a live, data-driven way, resulting in limited visibility into project health and insufficient actionable evidence for decision-making and future tenders. | F32: Projects continuously generate data such as models, deliverables, hours, progress, budget consumption, and design iterations, but this data is not systematically linked to indicators that reflect project status and development. Project performance is therefore assessed anecdotally, and tender teams cannot draw on reliable quantitative benchmarks from past projects. | G32: Enable AI and automation; Project write-downs; Tender competitiveness | H32: 10 | I32: 1 | J32: =Problems[[#This Row],[Cross_Unit_ProblemRelevance_Count]]+Problems[[#This Row],[Pri signal, by voting (WS1, 8-26)]] -> 11 | K32: 0 | L32: N/A | M32: ESP-S028 ProjectWise dashboards and Teams reporting (UK&I) | N32: Not indicated | O32: MP | P32: Recognised | Q32: Recognised | R32: No known relevance | S32: needs checking | T32: Recognised | U32: No known relevance | V32: Experienced | W32: ESP-S028 Makes system activity, workflow status, file activity, user information, and project-specific measures visible through operational dashboards and reporting. | X32: 2026-08 Workshop_1_problem_register.xlsx | Y32: Problem register | Z32: Imported | AC32: Not reviewed | AG32: Workshop 1 problem
J33: =Problems[[#This Row],[Cross_Unit_ProblemRelevance_Count]]+Problems[[#This Row],[Pri signal, by voting (WS1, 8-26)]] -> 0
N42: S

Sheet Existing Practices
A1: Existing local standards and practices
A2: Imported practices retain Practice ID (ESP-S###) and preserve Derived problem ID (ESP-P###) as the existing ESP reference.
A5: Practice ID | B5: Derived problem ID | C5: Category | D5: Contact | E5: Practice title | F5: Unit using solution | G5: Loc. used | H5: Current Footprint | I5: Adoption (inferred) | J5: Maturity (inferred) | K5: Ownership (inferred) | L5: Cross-unit interest (validated) | M5: Scalability judgment (inferred) | N5: Unit relevance of problems solved (OAG WS 30.06.2026) | O5: In Top 5-10 of problems to solve for untis (OAG WS30.06.26) | P5: Unit_Relevance_Count_WS_06_2026 | Q5: Problem category(ies) | R5: Problem statement | S5: How the existing solution solves problem(s) | T5: Value it appears to give | U5: Value it appears to give - Any other comments | V5: Adoption across relevant projects | W5: Adoption - Any other comments | X5: Maturity Status | Y5: Maturity - Any other comments | Z5: Ownership2 | AA5: Ownership - Any other comments | AB5: Scaling Judgement | AC5: Scaling Judgement in 04-26 workshop - Any other comments | AD5: What does it consist of? | AE5: What does it consist of? - Key tools involved | AF5: What does it consist of? - Any other comments | AG5: For which project types can it be valuable? | AH5: In which project types is it valuable - Any other comments | AI5: Assumptions on scalability (based on discussions and Miro) - Comments | AJ5: Where it could be useful | AK5: Barriers/concerns | AL5: Barriers/concerns - Any other comments | AM5: Column1 | AN5: Source File | AO5: Source Sheet | AP5: Record Origin | AQ5: AIConfidence | AR5: ConfidenceReason | AS5: ReviewStatus | AT5: Reviewer | AU5: ReviewerComments | AV5: ReviewDecisionID | AW5: Source Type
A6: ESP-S001 | B6: ESP-P001 | C6: Governance | D6: Allan Rasmussen | E6: ProjectWise (CDE) manager governance model (Denmark) | F6: Denmark;# | G6: DK | H6: Denmark transport & water projects, 66 local managers | I6: High | J6: High (inferred) | K6: Clear | L6: High | M6: High | N6: Sweden, UK&I, Denmark, Major Projects | P6: 4 | Q6: Project startup is unclear/slow;#Inconsistent use of standards/templates;#Poor onboarding of new team members;# | R6: Without a qualified CDE manager supporting the project, it can start slowly and not following the current best practice or standard | S6: A named department PW manager is available for projects to support setup and access, and keeping the PW structure consistent across projects. PW manager model enables community and to support each other through vacation and alike off time. | T6: Faster / clearer project startup;#Better compliance / consistency;#Improved transparency for PMs / teams;#. Community enabels people to get assistance from other PW managers and Bentley team when needed (distributed knowledge). | U6: Projects get a consistent setup, and users know who owns access and day-to-day administration. Can get support form other PW Managers if in need. | V6: Used in most or nearly all relevant projects;# | W6: ProjectWise managers create projects directly and have overview of the projects. | X6: Ad hoc and operational;# | Y6: Transcript says the model has been built on the same standard since 2011, works really well, and there are now 66 ProjectWise managers. | Z6: Clear and role-based;# | AA6: There are 66 local ProjectWise managers; they create projects, manage project access and keep the project overview, with the Denmark admin team supporting the model. | AB6: Clearly worth deeper analysis;# | AC6: Strong operational model with clear ownership and visible reuse potential across geographies. | AD6: Process/way of working;#Role or governance model;# | AE6: ProjectWise | AF6: 66 local ProjectWise managers create projects, manage access, and maintain project-level oversight using a shared standard and defined permission levels. | AG6: All projects;# | AI6: Miro feedback suggests this role-and-permission model could be useful beyond Denmark as part of a broader CDE standard. | AJ6: Global relevance flagged;# | AK6: Resource/capacity constraints;# | AL6: The model relies on trained local managers having time available alongside project work. | AN6: Existing standards register_RTR Master.xlsx | AO6: Existing practice register | AP6: Imported | AS6: Not reviewed | AW6: Existing practice
A7: ESP-S002 | B7: ESP-P002 | C7: Governance | D7: Allan Rasmussen | E7: ProjectWise manager guide and standards portal (Denmark) | F7: Denmark;# | G7: DK | H7: Denmark ProjectWise environments, all manager network | I7: High | J7: High | K7: Clear | L7: High | M7: High | N7: Norway, Sweden, UK&I, Major Projects | O7: Sweden | P7: 5 | Q7: Project startup is unclear/slow;#Inconsistent use of standards/templates;#Poor onboarding of new team members;# | R7: Project teams rely on informal and individual knowledge when setting up the CDE, leading to waste of time in the start of the project and downstream efficiency and quality risks | S7: The guide standardises how PW managers create and support projects, and helps users find the right project contact quickly. | T7: Faster / clearer project startup;#Better compliance / consistency;# | U7: It reduces reliance on informal knowledge by documenting the setup steps and manager network in one place. | V7: Used in most or nearly all relevant projects;# | W7: The guide and portal are presented as the standard information source for ProjectWise managers. | X7: Robust;# | Y7: The guide is described as not new, but still working really well and giving managers a good way to do it right. | Z7: Clear and role-based;# | AA7: The guide was made by the Denmark ProjectWise admin team/colleagues and is used by local ProjectWise managers. | AB7: Clearly worth deeper analysis;# | AC7: Good candidate for reuse as a lightweight coordination layer around CDE standards. | AD7: Templates/standards;#Process/way of working;# | AE7: SharePoint, ProjectWise | AF7: A portal page and guide give ProjectWise managers contact lists, step-by-step instructions, and standard setup guidance. | AG7: All design projects;# | AI7: Miro notes specifically highlighted the portal approach to standards, administrators, and training material as reusable. | AJ7: Global relevance flagged;# | AK7: Adoption & change resistance;# | AL7: Scaling would require teams to keep the guidance current and use the shared portal rather than local workarounds. | AN7: Existing standards register_RTR Master.xlsx | AO7: Existing practice register | AP7: Imported | AS7: Not reviewed | AW7: Existing practice
A8: ESP-S003 | B8: ESP-P003 | C8: Production Environments & Configurations | D8: Allan Rasmussen | E8: ProjectWise for production - RAMDK (Denmark) | F8: Denmark;# | G8: DK | H8: Denmark transport & water design | I8: High | J8: High | K8: Clear | L8: High | M8: High | N8: Norway, Sweden, UK&I, Denmark | O8: Denmark | P8: 5 | Q8: Inconsistent use of standards/templates;#External collaboration friction;#Poor onboarding of new team members;# | R8: Users struggle when CDEs are set up differently across projects | S8: Users see the same structure from project to project, and external access can be controlled through the defined setup. Recognisable structure and corresponding gides enables shared workforce engagement with limited need according to project introduction. | T8: Better compliance / consistency;#Easier collaboration externally;#Improved transparency for PMs / teams;# | U8: The Denmark team described it as mature and stable, with very few issues when projects follow the standard. | V8: Used in most or nearly all relevant projects;# | W8: Presented as the core production environment for Denmark transport & water areas in ProjectWise. Energy GBA also use the PW environment at hig scale. | X8: Robust;# | Y8: The production environment started in 2011 and was described as working well, with very rare issues when the standard is followed. | Z8: Clear and role-based;# | AA8: The Denmark ProjectWise production environment is run by the Denmark Bentley team responsible for the RAMDK environment. | AB8: Clearly worth deeper analysis;# | AC8: Established working model with strong practical evidence from Denmark. | AD8: Platform setup (CDE, hub, workspace);#Templates/standards;#Role or governance model;# | AE8: ProjectWise | AF8: On-prem production environment in Copenhagen, in use since 2011, with standard project structures, permission groups, support for externals, and repeatable project creation. | AG8: All design projects;# | AI8: Miro notes highlighted standards implemented in the CDE and a standard way of managing CDEs and projects as having broader potential. | AJ8: Global relevance flagged;# | AK8: Tool/platform dependencies;# | AL8: Workshop discussion highlighted dependency on Bentley and Civil 3D integration, especially when new versions are released. | AN8: Existing standards register_RTR Master.xlsx | AO8: Existing practice register | AP8: Imported | AS8: Not reviewed | AW8: Existing practice
A9: ESP-S004 | B9: ESP-P004 | C9: Production Environments & Configurations | D9: Allan Rasmussen | E9: Managed workspace in ProjectWise (Denmark) | F9: Denmark;# | G9: DK | H9: Denmark design projects using Bentley tools | I9: High | J9: High | K9: Clear | L9: Medium | M9: Medium | N9: Norway, Sweden, UK&I | P9: 3 | Q9: Inconsistent use of standards/templates;#Shared workforce/cross-country delivery barriers;# | R9: It is cumbersome for users to apply the right tool configurations and templates for the project at hand, leading to time waste and quality issues | S9: It helps ensure the same tools and setup are available wherever the project is opened, including by colleagues in other locations. Recognisable structure between projects and guides enables faster and easier project onboarding | T9: Better compliance / consistency;#Enables sharing people across projects/countries;# | U9: The Denmark team described this as a key strength for consistent delivery and collaboration across locations. | V9: Used in many relevant projects;# | W9: The entire setup was described as being in ProjectWise so right tools are used when users open the project and files. | X9: Operational;# | Y9: Managed workspace was described as one of the great strengths of the hosted environment and as the way their setup is delivered through ProjectWise. | Z9: Exists but person dependent;# | AA9: The Denmark team maintains the managed workspace content and project-specific setup delivered through ProjectWise. | AB9: Clearly worth deeper analysis;# | AC9: Strong candidate where common setup and workforce sharing are important. | AD9: Platform setup (CDE, hub, workspace);#Templates/standards;# | AE9: ProjectWise managed workspace, Bentley tools | AF9: Tooling, menus, support files, and selected project-specific setup are delivered through the ProjectWise workspace so users opening the project get the relevant environment. | AG9: All design projects;# | AI9: Miro notes highlighted CDE standards and follow-up on similarities between ProjectWise setup and CAD menus as a scaling area. | AJ9: Global relevance flagged;# | AK9: Tool/platform dependencies;# | AL9: Scaling depends on reliable integrations and ongoing maintenance of the managed workspace content. Relies on close involvement and time from business side to ensure cross discipline coordination and alignemnt. | AN9: Existing standards register_RTR Master.xlsx | AO9: Existing practice register | AP9: Imported | AS9: Not reviewed | AW9: Existing practice
A10: ESP-S005 | B10: ESP-P005 | C10: Project Setup & Coordination | D10: Jeppe Bæklund | E10: CAD project manual and transport standards portal (Denmark) | F10: Denmark;# | G10: DK | H10: Denmark transport projects, all disciplines | I10: High | J10: Medium | K10: Clear | L10: High | M10: High | N10: Norway, Sweden, UK&I, Denmark, Major Projects | O10: UK&I, Denmark | P10: 7 | Q10: Project startup is unclear/slow;#Inconsistent use of standards/templates;#Poor onboarding of new team members;# | R10: Projects and users lose time and consistency when there is no CAD/BIM standards or it is difficult to find the correct ones. Projects and users lose time and consistency when there no sufficiently experienced person in place to create/provide CAD/BIM standards meaning project standards are not in place. | S10: The portal provides one reference point for how projects should be set up and how discipline outputs should be structured. | T10: Faster / clearer project startup;#Better compliance / consistency;# | U10: Projects can state that they follow the standard setup, then only document exceptions where needed. | V10: Used in many relevant projects;# | W10: The manual and portal were described as the reference point for how projects should be set up. | X10: Operational;# | Y10: Every project is expected to have a CAD project manual, supported by the transport standards portal. | Z10: Exists but person dependent;# | AA10: The transport portal/standards content sits with a BIM team inside the Danish transport organisation. | AB10: Clearly worth deeper analysis;# | AC10: Useful model for project setup guidance, but would benefit from stronger communication and maintenance. | AD10: Templates/standards;#Process/way of working;# | AE10: SharePoint | AF10: Projects are expected to use a CAD project manual, supported by a transport portal with standards, naming, coordinate systems, drawing setup, and client-specific guidance. | AG10: All design projects;# | AI10: Miro notes highlighted the portal approach as reusable and also noted Denmark still lacks a fully standard good way of distributing product information. | AJ10: Global relevance flagged;# | AK10: Adoption & change resistance;# | AL10: The workshop noted that communication and distribution of product information is still an area to improve. | AN10: Existing standards register_RTR Master.xlsx | AO10: Existing practice register | AP10: Imported | AS10: Not reviewed | AW10: Existing practice
A11: ESP-S006 | B11: ESP-P006 | C11: Project Setup & Coordination | D11: Allan Rasmussen | E11: Teams-based product information and support channel (Denmark) | F11: Denmark;# | G11: DK | H11: Denmark transport tool users | I11: Low | J11: Low | K11: Clear | L11: High | M11: Medium | N11: Finland, Sweden, UK&I, Major Projects | O11: Finland | P11: 5 | Q11: Poor onboarding of new team members;#Inconsistent use of standards/templates;# | R11: Users miss important tool updates and support guidance when there is not a formal single source of truth information channel for the tool | S11: It gives users a visible place to find updates and communicate around tools and ways of working. | T11: Improved transparency for PMs / teams;# | U11: The team described communication as an ongoing challenge, but the Teams channel is one of the current mechanisms for reaching users. | W11: The channel is one of the current mechanisms for product information, but communication was described as an area still being worked on. | X11: Developing;# | Y11: The Teams channel is in use, but the team also said they are still struggling with how to communicate updates broadly. | AB11: Potential, but needs clarification;# | AC11: Promising support layer, though the workshop noted Denmark still can optimise areas to accomodate fully standard way of distributing product information. | AD11: Process/way of working;#Templates/standards;# | AE11: Microsoft Teams | AF11: A Teams channel is used to publish updates, tips and tricks, release information, product issues, and support guidance for transport tools. | AI11: Miro feedback suggests the communication and portal pattern has reuse potential, but adoption depends on people actively using the channel. | AJ11: Global relevance flagged;# | AK11: Adoption & change resistance;# | AL11: Value depends on users checking the channel and on teams having a clear communications model. | AN11: Existing standards register_RTR Master.xlsx | AO11: Existing practice register | AP11: Imported | AS11: Not reviewed | AW11: Existing practice
A12: ESP-S007 | B12: ESP-P007 | C12: Governance | E12: Client-led data management and modelling instruction model (Finland) | F12: Finland;# | G12: FI | H12: Finland major transport projects with clients | I12: High | J12: Medium | K12: Partly clear | L12: High | M12: Medium | N12: Finland, Norway, Sweden, UK&I, Denmark, Major Projects | O12: Finland, Norway, UK&I | P12: 9 | Q12: Inconsistent use of standards/templates;#Poor onboarding of new team members;# | R12: Teams risk inconsistent data delivery when client modelling requirements are interpreted differently or not translated into clear project setup rules. | S12: Client instructions and project data-management plans give projects a defined baseline for setup, naming, deliverables, and modelling expectations. Clients have their standards documented. | T12: Better compliance / consistency;# | U12: It creates a common minimum standard on projects even though requirements vary by client and project type. | V12: Used in most or nearly all relevant projects;# | W12: Described as the baseline approach on major transport projects, though requirements vary by client. Clients require the use of their standards. | X12: Operational;# | Y12: Projects follow client and agency instructions, but the transcript also indicates requirements vary by client and project type, so ownership and support are not yet consistent enough to call this fully operational. | AB12: Potential, but needs clarification;# | AC12: Strong as a governance pattern, but not yet a directly portable standard without simplification. Standards have ideas that can be scaled, but standards are tied to clients own systems and Finnish law. | AD12: Templates/standards;#Process/way of working;# | AE12: SharePoint, client data management plans | AF12: Major transport projects follow client and agency modelling/data-management instructions, and project documentation records how data should be structured and delivered. | AG12: Specific project types;# | AH12: Major transport projects | AI12: Reuse outside Finland is possible at the pattern level, but Miro feedback and the workshop both suggest client-specific variation is a major limiter unless the core common elements are separated from local requirements. | AK12: Governance/ownership unclear;#Local regulations/client constraints;# | AL12: Ownership is split across clients, project teams, and discipline leads, and client-specific requirements can materially change the setup. | AN12: Existing standards register_RTR Master.xlsx | AO12: Existing practice register | AP12: Imported | AS12: Not reviewed | AW12: Existing practice
A13: ESP-S008 | B13: ESP-P008 | C13: Production Environments & Configurations | E13: Quadri / Trimble Connect project environment (Finland) | F13: Finland;# | G13: FI | H13: Finland transport infrastructure projects | I13: Medium | J13: Medium | K13: Partly clear | L13: Medium | M13: Medium | N13: Finland, Norway, Sweden, UK&I, Denmark, Major Projects | O13: Finland, Norway, Major Projects | P13: 9 | Q13: Inconsistent use of standards/templates;#Shared workforce/cross-country delivery barriers;# | R13: Shared delivery is difficult when project environments vary by client, complexity and who sets them up, even when the same core tools are used. | S13: The environment gives projects a repeatable structure, but setup still varies with client requirements, project complexity, and who is doing the setup. | T13: Better compliance / consistency;#Enables sharing people across projects/countries;# | U13: A shared environment and standard base structure make it easier for multiple teams to work in the same project context. | V13: Used in many relevant projects;# | W13: Presented as a common structured project environment in Finland transport projects. | X13: Operational;# | Y13: Projects are commonly created through a service request for Quadri / Trimble Connect. | Z13: Exists but person dependent;# | AA13: The project manager orders the project, then setup is commonly delegated to the BIM coordinator or project assistant; they order the Quadri project and handle the real folder setup. | AB13: Potential, but needs clarification;# | AC13: Promising operational model, though still closely tied to the current Finland toolchain. | AD13: Platform setup (CDE, hub, workspace);#Templates/standards;# | AE13: Quadri, Trimble Connect, ServiceNow | AF13: Projects are commonly created through a service request, with folder structures, naming, and base setup coming from Finnish configuration and customer-specific requirements. | AG13: All design projects;# | AI13: This looks scalable where other countries need a structured infra design environment, but the Miro discussion suggests broader rollout would need stronger support and clearer handling of the choose-best-tool tension. | AK13: Tool/platform dependencies;# | AL13: Scaling depends on Trimble/Quadri tooling, Finnish-specific setup conventions, and support capability across teams and geographies. | AN13: Existing standards register_RTR Master.xlsx | AO13: Existing practice register | AP13: Imported | AS13: Not reviewed | AW13: Existing practice
A14: ESP-S009 | B14: ESP-P009 | C14: Production Environments & Configurations | E14: Finnish configuration packages for design tools (Finland) | F14: Finland;# | G14: FI | H14: Finland design projects, fragmented adoption | I14: Low | J14: Low | K14: Partly clear | L14: High | M14: Low | N14: Finland, Norway, Sweden, UK&I, Major Projects | O14: Major Projects | P14: 6 | Q14: Inconsistent use of standards/templates;#Poor onboarding of new team members;# | R14: Projects waste time and struggle with inconsistency when there is not a standard package of tools and tool configurations, and users apply configurations stored locally on their computer | S14: The configuration gives designers a starting point, but discipline-specific variations and locally hidden templates still create inconsistency. | T14: Better compliance / consistency;#Faster / clearer project startup;# | U14: Where the package is maintained and used properly, it reduces manual setup and gives teams a more repeatable starting point. | V14: Used in some relevant projects;# | W14: Teams are trying to use existing configurations as much as possible, but the approach was described as fragmented. | X14: Developing;# | Y14: Configurations exist and are used, but fragmented ownership, hidden templates, and manual tweaking were all discussed. | Z14: Exists but person dependent;# | AA14: Tool administrators such as Timo and Aleksi maintain and publish configurations, super-users are the main contacts, and Arkance provides support/training and some tool packages. | AB14: Potential, but needs clarification;# | AC14: Valuable core capability, but the current governance model is not yet strong enough for easy reuse at scale. | AD14: Templates/standards;#Platform setup (CDE, hub, workspace);# | AE14: Novapoint, AutoCAD Map 3D, Civil 3D, Arkance tools, 3D-Win | AF14: Finnish configurations package templates, naming, drawings, client definitions, and support files into the installed tool setup, although some manual tweaking is still often required. | AI14: Miro notes highlighted the broader challenge of standardising while still allowing teams to choose the best tool, so scaling this approach likely requires stronger central ownership of shared configurations. | AK14: Governance/ownership unclear;#Conflicts with “choose best tool” principle;# | AL14: The workshop described fragmented ownership, locally held templates, and mixed-tool working as key barriers to consistent deployment. | AN14: Existing standards register_RTR Master.xlsx | AO14: Existing practice register | AP14: Imported | AS14: Not reviewed | AW14: Existing practice
A15: ESP-S010 | B15: ESP-P010 | C15: Production Environments & Configurations | E15: Forma pilot with discipline templates (Finland) | F15: Finland;# | G15: FI | H15: Finland railway & highway projects, pilot phase | I15: Low | J15: Low | K15: Partly clear | L15: High | M15: Low | N15: Finland, Norway, Sweden, UK&I, Denmark | P15: 5 | Q15: Project startup is unclear/slow;#Inconsistent use of standards/templates;# | R15: New projects take longer to mobilise when disciplines lack standard or have incomplete project templates | S15: The pilot is intended to make project creation more standardised and easier to connect with the broader Finland setup approach. | T15: Better compliance / consistency;# | U15: The workshop described Forma as a potential turning point for reducing variation, but it is still early and benefits have not yet been proven in live delivery at scale. | V15: Used in a small minority of relevant projects;# | W15: Discipline templates exist, but the solution was explicitly presented as a pilot. | X15: Developing;# | Y15: Forma was described as being piloted, with piloting starting next week or shortly after. | Z15: Exists but person dependent;# | AA15: Timo and Aleksi are owners of the Finnish templates, Disciplines themselves define how the template should be configurated. | AB15: Potential, but needs clarification;# | AC15: Interesting strategic direction, but less proven than the existing Finland setup practices. | AD15: Platform setup (CDE, hub, workspace);#Templates/standards;# | AE15: Forma, ACC | AF15: Forma is being piloted, with home templates already prepared for railway and highway projects and an ambition to add client-specific templates over time. | AG15: Specific project types;# | AH15: Railway and highway projects | AI15: The discussion suggests clear potential if the pilot matures, but there is not yet enough evidence to treat it as an established Finland standard. | AJ15: Mixed/unclear signals;# | AK15: Tool/platform dependencies;#Adoption & change resistance;# | AL15: It is still early, and success will depend on implementation effort, user uptake, and how well Forma fits alongside existing Finland tools and client constraints. | AN15: Existing standards register_RTR Master.xlsx | AO15: Existing practice register | AP15: Imported | AS15: Not reviewed | AW15: Existing practice
A16: ESP-S011 | B16: ESP-P011 | C16: Project Setup & Coordination | E16: Transport software standards portal and Teams communication channels (Finland) | F16: Finland;# | G16: FI | H16: Finland transport software users nationwide | I16: Low | J16: Medium | K16: Clear | L16: High | M16: High | N16: Finland, Norway, Sweden, UK&I | P16: 4 | Q16: Poor onboarding of new team members;#Inconsistent use of standards/templates;# | R16: People struggle to find and trust the latest software and standards guidance if there is not a trusted single source of truth information channel for it | S16: It gives users one place to look for current guidance and a visible route for software communication and support. | T16: Improved transparency for PMs / teams;#Better compliance / consistency;# | U16: The portal reduces ambiguity about where to find instructions, and the Teams channel helps distribute current information quickly. | W16: The software site was described as the one place users should go for software information and guidance. | X16: Operational;# | Y16: Finland has a transport software SharePoint site and Teams channels in use now, with the site upgraded recently. | Z16: Exists but person dependent;# | AA16: Timo and Aleksi are owners of the Finland transport software SharePoint/Teams site. Superusers are producing the material | AB16: Clearly worth deeper analysis;# | AC16: Strong practical candidate for reuse as a lightweight communication and standards layer. | AD16: Templates/standards;#Process/way of working;# | AE16: SharePoint, Microsoft Teams | AF16: Finland transport uses a SharePoint site for software guidance, templates, installation instructions, and support services, while Teams channels are used for updates such as outages and release information. | AG16: All design projects;# | AI16: Miro feedback pointed to the importance of formal information channels and clearer responsibility on users to stay informed, suggesting this pattern has wider relevance if it is actively maintained. | AJ16: Global relevance flagged;# | AK16: Adoption & change resistance;# | AL16: The model only works if users know it exists, trust it as the single source of truth, and are expected to use it rather than local copies and side channels. | AN16: Existing standards register_RTR Master.xlsx | AO16: Existing practice register | AP16: Imported | AS16: Not reviewed | AW16: Existing practice
A17: ESP-S012 | B17: ESP-P012 | C17: Governance | E17: Super-user network and office roadshow support model (Finland) | F17: Finland;# | G17: FI | H17: Finland offices using tool configurations | I17: Low | J17: Medium | K17: Clear | L17: High | M17: Medium | N17: Norway, Sweden, UK&I, Major Projects | O17: Sweden, UK&I | P17: 6 | Q17: Poor onboarding of new team members;#Inconsistent use of standards/templates;# | R17: Standards do not stick and improve when there are no local go-to people / superusers to ask for guidance and who can route feedback to the relevant owners. Standards do not stick and improve when there are no sufficiently experienced local go-to people / superusers to ask for guidance and who can route feedback to the relevant owners in an understandable way. | S17: The model helps surface local issues, spread updates, and reinforce expected ways of working in a fragmented environment. | T17: Better compliance / consistency;#Improved transparency for PMs / teams;# | U17: This is one of the ways Finland keeps standards alive in practice, especially where passive communications alone are not enough. | W17: The model is active today, with visits to offices and use of super-users as the virtual team. | X17: Operational;# | Y17: They described yearly roadshows and super-users as the main contacts for maintaining and improving standards. | Z17: Exists but person dependent;# | AA17: Super-users are the main contacts for the support admins when configurations and standards need maintenance. | AB17: Potential, but needs clarification;# | AC17: Useful change-enablement model, though hard to scale without dedicated capacity. | AD17: Process/way of working;#Role or governance model;# | AE17: SharePoint, super-user network, office roadshows | AF17: Support admins use super users as their main contacts, visit offices, and gather updates and pain points directly from teams to improve standards and guidance. | AI17: The workshop and Miro comments both point to change management as a core challenge, so this support model could be useful elsewhere where communication and adoption are the real bottlenecks. | AJ17: Global relevance flagged;# | AK17: Resource/capacity constraints;#Adoption & change resistance;# | AL17: Its effectiveness depends heavily on a small number of people having time to do outreach, follow-up, and continuous support. | AN17: Existing standards register_RTR Master.xlsx | AO17: Existing practice register | AP17: Imported | AS17: Not reviewed | AW17: Existing practice
A18: ESP-S013 | B18: ESP-P013 | C18: Production Environments & Configurations | E18: Integrated multi-platform project environment (Norway) | F18: Norway;# | G18: NO | H18: Norway major rail & highway infrastructure | I18: High | J18: Medium | K18: Partly clear | L18: High | M18: High | N18: Finland, Norway, Sweden, UK&I, Denmark, Major Projects | O18: Norway, UK&I, Denmark, Major Projects | P18: 10 | Q18: Shared workforce/cross-country delivery barriers;#External collaboration friction;#Inconsistent use of standards/templates;# | R18: Lack of standardised connected ecosystems of design tools, CDEs, issue mgmt and client platforms, required for complex projects createa s slow and costly process for setting up the project production environment | S18: The setup supports high-trust collaboration with clients and contractors, but the overall ecosystem is complex and varies by project and client. | T18: Enables sharing people across projects/countries;#Easier collaboration externally;#Improved transparency for PMs / teams;# | U18: The Norway team described this as the practical way they keep multi-platform major projects working across internal and external parties. | V18: Used in most or nearly all relevant projects;# | W18: Presented as the common model for major Norwegian rail and highway projects. | X18: Developing;# | Y18: Used on major projects, but the transcript describes a complex multi-platform setup that depends heavily on dedicated digital project role resources bridging systems, so it is not yet a low-friction standard model. | Z18: Exists but person dependent;# | AA18: The major Norwegian projects have dedicated full-time BIM resources / a BIM group handling much of the digital infrastructure between systems. | AB18: Clearly worth deeper analysis;# | AC18: Strong example of a real multi-platform delivery model, but not a lightweight one to replicate. | AD18: Platform setup (CDE, hub, workspace);#Process/way of working;# | AE18: ProjectWise, ACC, Trimble Connect, Azure, Jira, ArcGIS | AF18: Major Norwegian rail and highway projects use a connected setup across several platforms, with BIM resources bridging the gaps between design tools, CDEs, issue management, and stakeholder collaboration. | AG18: Specific project types;# | AH18: Major rail and highway projects | AI18: The workshop showed this as an effective operating pattern for complex projects, but scaling it more widely would require stronger standardisation across tools, clients, and startup practices. | AJ18: Global relevance flagged;# | AK18: Tool/platform dependencies;#Local regulations/client constraints;# | AL18: The model depends on several connected platforms and on client-specific ways of working, especially in major infrastructure projects. | AM18: Under revision | AN18: Existing standards register_RTR Master.xlsx | AO18: Existing practice register | AP18: Imported | AS18: Not reviewed | AW18: Existing practice
A19: ESP-S014 | B19: ESP-P014 | C19: Production Environments & Configurations | E19: BIMbot model exchange and automation layer (Norway) | F19: Norway;# | G19: NO | H19: Norway major projects across multiple platforms | I19: Low | J19: Medium | K19: Partly clear | L19: High | M19: High | N19: Norway, Sweden, UK&I, Denmark | O19: Norway, Denmark | P19: 6 | Q19: Shared workforce/cross-country delivery barriers;#Inconsistent use of standards/templates;#Poor onboarding of new team members;# | R19: Projects waste effort and risk outdated design models when interdisciplinary model exchanges still depend on manual exporting, importing and checking between platforms | S19: It was created to reduce manual exports and imports between tools and to keep live interdisciplinary models available to teams. | T19: Enables sharing people across projects/countries;#Better compliance / consistency;#Improved transparency for PMs / teams;# | U19: The automation gives teams updated model information across platforms and reduces repetitive manual coordination work. | V19: Used in some relevant projects;# | W19: It was presented as the automation layer used to move models and files between platforms in major projects. | X19: Operational;# | Y19: BIMbot has been in place for years and now connects several platforms automatically. | Z19: Exists but person dependent;# | AB19: Clearly worth deeper analysis;# | AC19: One of the clearest Norway candidates for wider reuse because it solves a recurring cross-platform problem. | AD19: Automation/dashboard;#Platform setup (CDE, hub, workspace);# | AE19: BIMbot, ProjectWise, ACC, Trimble Connect, SharePoint, Teams | AF19: BIMbot moves files automatically between platforms and can also extract, merge, split, and check IFC data, helping disciplines receive updated models without manual file handling. | AG19: Specific project types;# | AH19: Major projects | AI19: Miro feedback explicitly flagged BIMbot as scalable, including as a broader tool for exporting, checking, and handling IFCs from design tools. | AJ19: Global relevance flagged;# | AK19: Tool/platform dependencies;#Resource/capacity constraints;# | AL19: Scaling depends on automation ownership, maintenance capacity, and stable integrations across the connected platforms. | AN19: Existing standards register_RTR Master.xlsx | AO19: Existing practice register | AP19: Imported | AS19: Not reviewed | AW19: Existing practice
A20: ESP-S015 | B20: ESP-P015 | C20: Governance | E20: Model Maturity Index (MMI) and property set standard (Norway) | F20: Norway;# | G20: NO | H20: Norway rail & highway model-based delivery | I20: Low | J20: Medium | K20: Clear | L20: Medium | M20: High | N20: Major Projects | P20: 1 | Q20: Inconsistent use of standards/templates;#External collaboration friction;# | R20: Lack of confidence and trust in the design models readiness for supporting the intended project decisions, use cases and delivery is unclear across the phases of design maturation | S20: The matrix makes model readiness clearer for clients and other disciplines, while giving a more contractual definition of what to expect at each stage. | T20: Better compliance / consistency;#Improved transparency for PMs / teams;# | U20: The team described this as a practical way to clarify maturity, readiness, and information expectations in model-based delivery. | V20: Used in some relevant projects;# | W20: It was described as becoming part of the contract in projects where it is used. | X20: Operational;# | Y20: Norway uses an MMI approach and has supplemented it with property sets and concrete matrices in projects. | Z20: Clear and role-based;# | AB20: Clearly worth deeper analysis;# | AC20: Strong candidate for reuse because it addresses a common ambiguity in model-based projects: what a model is actually ready for. | AD20: Templates/standards;#Process/way of working;# | AE20: MMI matrix, IFC property sets, discipline model standards | AF20: Norway uses an MMI approach to define what each discipline model can be used for at each stage, combined with structured property sets that specify what information should be populated. | AG20: Specific project types;# | AH20: Rail and highway projects | AI20: Miro notes specifically highlighted MMI and IFC 4x3 property-set know-how as reusable, especially for other geographies developing stronger model-based delivery standards. | AJ20: Global relevance flagged;# | AK20: Adoption & change resistance;#Governance/ownership unclear;# | AL20: Value depends on consistent discipline use, shared understanding of the maturity definitions, and agreement on common property structures. | AN20: Existing standards register_RTR Master.xlsx | AO20: Existing practice register | AP20: Imported | AS20: Not reviewed | AW20: Existing practice
A21: ESP-S016 | B21: ESP-P016 | C21: Project Setup & Coordination | E21: Project onboarding form and access workflow (Norway) | F21: Norway;# | G21: NO | H21: Norway major and complex multi-tool projects | I21: High | J21: Medium | K21: Partly clear | L21: High | M21: High | N21: Norway, Sweden, UK&I, Denmark, Major Projects | O21: Norway, Sweden | P21: 7 | Q21: Project startup is unclear/slow;#Poor onboarding of new team members;#External collaboration friction;# | R21: Project onboarding is slow and hard to track when user access, approvals and offboarding are handled through ad hoc email chains and teams chats | S21: The workflow replaces ad hoc email chains and gives projects a clearer, traceable onboarding process across multiple tools. | T21: Faster / clearer project startup;#Improved transparency for PMs / teams;# | U21: The team described it as a major improvement in larger projects where many users, externals, and tools need coordinated access. | V21: Used in most or nearly all relevant projects;# | W21: The team said it is used in all big projects and in quite a lot of other projects as well. | X21: Operational;# | Y21: The workflow is already used in all big projects and now in quite a lot of other projects as well. | Z21: Exists but person dependent;# | AA21: The project leader approves onboarding requests, tool admins grant access, and Andreas said he is still the main resource setting the solution up and usually the owner of it. | AB21: Clearly worth deeper analysis;# | AC21: Very promising candidate for reuse because it solves a common startup pain point with relatively familiar Microsoft tooling. | AD21: Process/way of working;#Automation/dashboard;# | AE21: Microsoft Forms, Power Automate, SharePoint lists, Teams | AF21: A project onboarding workflow lets project teams request users, approvals, and tool access through one process, with automated routing to project leaders and tool admins and support for offboarding dates. | AG21: Specific project types;# | AH21: Major / highly complex projects | AI21: Miro feedback explicitly highlighted the project onboarding form as having scaling potential globally and for Finland follow-up. | AJ21: Global relevance flagged;# | AK21: Resource/capacity constraints;#Governance/ownership unclear;# | AL21: The current setup works well but is still dependent on a small number of people and was not originally built as a fully scalable enterprise solution. | AN21: Existing standards register_RTR Master.xlsx | AO21: Existing practice register | AP21: Imported | AS21: Not reviewed | AW21: Existing practice
A22: ESP-S017 | B22: ESP-P017 | C22: Project Setup & Coordination | E22: Project SharePoint/Teams information hub (Norway) | F22: Norway;# | G22: NO | H22: Norway major and complex project teams | I22: Medium | J22: Medium | K22: Partly clear | L22: High | M22: High | N22: Norway, Sweden, UK&I | O22: Sweden | P22: 4 | Q22: Poor onboarding of new team members;#Project startup is unclear/slow;# | R22: New and existing team members lose time finding correct up-to-date project information when key links, guidance, updates and info on digital tools are scattered across project documents and storage | S22: The hub gives project members one visible entry point into a complicated multi-system project setup. | T22: Improved transparency for PMs / teams;#Faster / clearer project startup;# | U22: This was presented as a practical support layer around the project systems rather than a production environment itself. | V22: Used in many relevant projects;# | W22: Presented as a lightweight but common project support layer around the main systems. | X22: Developing;# | Y22: The hub is used in many projects, but the transcript presents it mainly as a lightweight support layer rather than a strongly governed, fully standardised operating model. | Z22: Exists but person dependent;# | AB22: Potential, but needs clarification;# | AC22: Useful enabling pattern, especially where projects span many tools and organisations. | AD22: Process/way of working;#Templates/standards;# | AE22: SharePoint, Microsoft Teams | AF22: Projects often use a SharePoint page surfaced through Teams as a one-stop place for key project links, news, progress information, and access to the main digital tools and project guidance. | AG22: Specific project types;# | AH22: Major / highly complex projects | AI22: The pattern aligns closely with Miro feedback from other countries about project hubs and is likely reusable where teams need a lightweight orientation and communication layer. | AJ22: Global relevance flagged;# | AK22: Adoption & change resistance;# | AL22: Its value depends on teams keeping the page current and using it as the shared reference point rather than relying on side channels. | AN22: Existing standards register_RTR Master.xlsx | AO22: Existing practice register | AP22: Imported | AS22: Not reviewed | AW22: Existing practice
A23: ESP-S018 | B23: ESP-P018 | C23: Production Environments & Configurations | E23: Asset coding and IFC 4x3 delivery pattern (Norway) | F23: Norway;# | G23: NO | H23: Norway road projects advancing asset delivery | I23: Low | J23: Low | K23: Partly clear | L23: High | M23: Medium | N23: Finland, Norway, Sweden, Major Projects | P23: 4 | Q23: Inconsistent use of standards/templates;#External collaboration friction;# | R23: Model-based project use cases and handover are harder when asset information are not coded and structured consistently, e.g. based on open standards like IFC 4x3 and applying standardised asset object coding | S23: This supports more model-based delivery and clearer handover into client systems, but it increases standardisation demands on disciplines. | T23: Better compliance / consistency;#Improved transparency for PMs / teams;# | U23: The Norway team described this as an important direction of travel, especially where clients are maturing toward model-based and asset-oriented delivery. | V23: Used in some relevant projects;# | W23: The approach is advancing, but they also said it is still difficult and time-consuming to implement. | X23: Developing;# | Y23: They said clients are doing more and more with object codes and asset-management style delivery, and Ramboll is getting closer on a couple of roads. | Z23: Exists but person dependent;# | AA23: For now, the BIM team handles much of the coding work for asset coding / IFC 4x3 delivery. | AB23: Potential, but needs clarification;# | AC23: Important strategic practice, though likely harder to scale quickly than the more lightweight support patterns. | AD23: Templates/standards;#Platform setup (CDE, hub, workspace);# | AE23: IFC 4x3, asset codes, client asset-management structures | AF23: Norwegian projects are moving toward model deliveries where each object carries structured codes and properties so the model can connect more directly into downstream asset-management processes. | AG23: Specific project types;# | AH23: Road projects | AI23: Miro notes highlighted knowledge around IFC 4x3 property sets as reusable, but the overall approach still appears more specialised than the onboarding and automation examples. | AJ23: Flagged for specific countries;# | AK23: Local regulations/client constraints;#Tool/platform dependencies;# | AL23: The approach is heavily influenced by client requirements, coding standards, and the maturity of the receiving asset-management environment. | AN23: Existing standards register_RTR Master.xlsx | AO23: Existing practice register | AP23: Imported | AS23: Not reviewed | AW23: Existing practice
A24: ESP-S019 | B24: ESP-P019 | C24: Production Environments & Configurations | D24: Jakob Holmquist | E24: CAD Configuration / Configuration Switch (Sweden) | F24: Sweden;# | G24: SE | H24: Sweden transport design projects | I24: Medium | J24: Low | K24: Partly clear | L24: High | M24: High | N24: Norway, Sweden, UK&I, Major Projects | O24: UK&I | P24: 5 | Q24: Inconsistent use of standards/templates;# | R24: Projects risk inconsistent CAD outputs and spend manual effort to find and adopt official/standard tool configurations and templates | S24: Supports consistent deployment of CAD configuration/templates to projects. | T24: Better compliance / consistency;# | U24: All configs and templates collected in the software and not in different libraries. | V24: Used in many relevant projects;# | W24: It was presented as the developed mechanism for templates and setup in Swedish projects. | X24: Developing;# | Y24: The configuration switch is the current Swedish deployment mechanism, but the transcript does not clearly evidence a mature governance, support, and maintenance model behind it. | Z24: Central administration run by Jakob Holmquist with redundancy in Simon Eriksson. Technical networks to provide relevant templates. | AA24: Could be owned globally by the Autodesk team | AB24: Potential, but needs clarification;# | AD24: Templates/standards;#Platform setup (CDE, hub, workspace);# | AE24: Configuration switch | AF24: Configuration mechanism used to deploy and access templates and setups. | AI24: Miro signals: Request process suggested as scalable. | AJ24: Global relevance flagged;# | AK24: Tool/platform dependencies;# | AN24: Existing standards register_RTR Master.xlsx | AO24: Existing practice register | AP24: Imported | AS24: Not reviewed | AW24: Existing practice
A25: ESP-S020 | B25: ESP-P020 | C25: Production Environments & Configurations | D25: Johan Fäldt | E25: Metadata and Naming + Managed Workspaces (Sweden) | F25: Sweden;# | G25: SE | H25: Sweden rail projects using ProjectWise | I25: Medium | J25: Low | K25: Partly clear | L25: High | M25: High | N25: Finland, Sweden, UK&I, Denmark, Major Projects | O25: Finland, Major Projects | P25: 7 | Q25: Inconsistent use of standards/templates;# | R25: CDE environments become harder to search, manage and reuse when metadata, naming and workspace setup are not standardised. | S25: Standardises naming and workspace setup within ProjectWise. | T25: Better compliance / consistency;# | V25: Used in many relevant projects;# | W25: Presented as part of the standard ProjectWise setup used primarily on rail projects. | X25: Developing;# | Y25: The transcript confirms Sweden uses metadata, naming, and managed workspaces in ProjectWise, but does not clearly show stable ownership, support, and repeatability beyond current practice. | AB25: Clearly worth deeper analysis;# | AD25: Templates/standards;#Platform setup (CDE, hub, workspace);# | AE25: ProjectWise | AF25: Use of metadata, naming conventions, and managed workspaces in ProjectWise environments. | AG25: Specific project types;# | AH25: Rail projects | AI25: Miro signals: Managed workspaces highlighted as reusable setup practice. Metadata raised as important to scale. | AJ25: Global relevance flagged;# | AK25: Tool/platform dependencies;# | AN25: Existing standards register_RTR Master.xlsx | AO25: Existing practice register | AP25: Imported | AS25: Not reviewed | AW25: Existing practice
A26: ESP-S021 | B26: ESP-P021 | C26: Production Environments & Configurations | D26: Samuel Wiklund | E26: ProjectWise (Rail Projects) (Sweden) | F26: Sweden;# | G26: SE | H26: Sweden rail projects including major ones | I26: Medium | J26: Low | K26: Partly clear | L26: Low | M26: Medium | N26: UK&I | P26: 1 | Q26: External collaboration friction;# | R26: Rail projects need controlled collaboration spaces; without them, external access, compliance and delivery coordination become harder to manage. | S26: Provides controlled production environment for rail project delivery. | T26: Better compliance/consistency;#Easier collaboration externally;# | V26: Used in many relevant projects;# | W26: ProjectWise was described as the primary environment for Swedish rail projects, including major projects. | X26: Developing;# | Y26: ProjectWise is used mainly for rail projects, including major ones, but the transcript gives limited evidence of the broader governance and support model needed for a higher maturity rating. | AD26: Platform setup (CDE, hub, workspace);# | AE26: ProjectWise | AF26: ProjectWise primarily used for rail projects, including major projects. | AG26: Specific project types;# | AH26: Rail projects | AI26: No scalability notes captured (please complete). | AK26: Tool/platform dependencies;# | AN26: Existing standards register_RTR Master.xlsx | AO26: Existing practice register | AP26: Imported | AS26: Not reviewed | AW26: Existing practice
A27: ESP-S022 | B27: ESP-P022 | C27: Project Setup & Coordination | D27: Joachim Schönström | E27: Opt-in model via project support SharePoint page (Sweden) | F27: Sweden;# | G27: SE | H27: Sweden major and multi-disciplinary projects | I27: Low | J27: Medium | K27: Clear | L27: High | M27: High | N27: Sweden, UK&I | O27: Sweden | P27: 3 | Q27: Project startup is unclear/slow;# | R27: Projects lose time at startup when it is difficult to find and activate support for setting up the a suitable production environment. | S27: Provides a clear intake/request route for setting up production environments. | T27: Faster/clearer project startup;# | V27: Used in some relevant projects;# | W27: Projects request the production platform through the support SharePoint page. | X27: Operational;# | Y27: The Sweden team described an opt-in model via the project support page, and said it is popular because the alternative is Filery. | Z27: Clear and role-based;# | AA27: The Design Excellence office supports startups through the SharePoint request page and startup support model. | AB27: Clearly worth deeper analysis;# | AC27: Miro flags the request process as scalable and it is described as an established opt-in model. | AD27: Process/way of working;#Platform setup (CDE, hub, workspace);# | AE27: SharePoint | AF27: Projects request production environments through a SharePoint-based support page (opt-in model). | AG27: Specific project types;# | AH27: Major / highly complex projects; multi-disciplinary projects | AI27: Miro signals: Request process suggested as scalable. | AJ27: Global relevance flagged;# | AK27: Governance/ownership unclear;# | AL27: Unclear file notes governance/ownership topics are still open for templates and standards. | AN27: Existing standards register_RTR Master.xlsx | AO27: Existing practice register | AP27: Imported | AS27: Not reviewed | AW27: Existing practice
A28: ESP-S023 | B28: ESP-P023 | C28: Project Setup & Coordination | D28: Joachim Schönström | E28: Project Hub (SharePoint coordination layer) (Sweden) | F28: Sweden;# | G28: SE | H28: Sweden major projects and production environments | I28: High | J28: Medium | K28: Clear | L28: High | M28: High | N28: Norway, Sweden, UK&I | O28: Sweden | P28: 4 | Q28: Poor onboarding of new team members;#External collaboration friction;# | R28: Project participants onboard slowly when information about project procedures, folder structures and live updates are not gathered and easily consumable in one place, and also made available in a different way in every new project. Also affecting project consistency in applying company standards and practices | S28: Provides a repeatable hub for project info and navigation, supporting onboarding and coordination. A visual and live project execution plan. Helps with training people in procedures, folder structure etc. | T28: Improved transparency for PMs/teams;#Easier collaboration externally;# | U28: A sense of project community, consistent information sharing, one point of entry. | V28: Used in most or nearly all relevant projects;# | W28: They said all major projects, and most projects with production environments, use the Project Hub setup. | X28: Operational;# | Y28: They said all major projects, and most projects with production environments, use the Project Hub setup. | Z28: Exists but person dependent;# | AA28: The templates/project hub are curated by the Sweden team in collaboration, within the Design Excellence office / startup support team. | AB28: Clearly worth deeper analysis;# | AC28: Miro flags GLOBAL relevance and interest from Finland and UK&I. | AD28: Process/way of working;#Templates/standards;#Platform setup (CDE, hub, workspace);# | AE28: SharePoint, Teams | AF28: SharePoint-based template used for project communication, onboarding, and navigation. | AG28: Specific project types;# | AH28: Recommended in all projects with >10 participants. Small effort to set up. | AI28: Miro signals: Project Hub identified as reusable/scalable. | AJ28: Global relevance flagged;#Flagged for specific countries;# | AK28: Governance/ownership unclear;#Adoption & change resistance;# | AL28: Unclear file highlights global standardisation ambition and communication strategy as open items for Project Hub. | AN28: Existing standards register_RTR Master.xlsx | AO28: Existing practice register | AP28: Imported | AS28: Not reviewed | AW28: Existing practice
A29: ESP-S024 | B29: ESP-P024 | C29: Project Setup & Coordination | E29: Early-phase digital delivery manager involvement (UK&I) | F29: UK&I;# | G29: UK&I | H29: UK&I early phase planning and design | I29: Low | J29: High | K29: Clear | L29: High | M29: High | N29: UK&I, Denmark, Major Projects | O29: Denmark | P29: 4 | Q29: Project startup is unclear/slow;#Inconsistent use of standards/templates;#Poor onboarding of new team members;# | R29: Projects can choose the wrong digital setup when digital delivery expertise (e.g. Digital Delivery Manager) is brought in after tender and mobilisation decisions are already made. | S29: The role is meant to bring digital requirements, CDE decisions, standards and risks into the project early enough that teams do not start in the wrong way of working. | T29: Faster / clearer project startup;#Better compliance / consistency;# | U29: Where it happens early, the UK&I team described it as the key route to choosing the right CDE and understanding client standards before delivery starts. | V29: Used in a small minority of relevant projects;# | W29: Only 4% of projects were said to engage early enough for the team to fully help. | X29: Developing;# | Y29: The process exists in the sales playbook, but Chris said only a small share of projects actually engage early enough. | Z29: Clear and role-based;# | AA29: The UK&I digital delivery managers are Helen Roberts, Katie Andrews, Chris Bargent and John Sadler. | AB29: Clearly worth deeper analysis;# | AC29: Strong front-end governance pattern, but current uptake in UK&I is far below the intended model. | AD29: Process/way of working;#Role or governance model;# | AE29: Early phase sales playbook, digital delivery manager role | AF29: A digital delivery manager is identified during DG1 and consulted through DG2 and DG3 to review tender documents, assess digital requirements, and guide project setup decisions before mobilisation. | AG29: Specific project types;# | AH29: Early phase planning and design | AI29: Miro explicitly highlighted the early involvement model as something other countries could reuse, but the transcript shows current adoption is still limited in practice. | AJ29: Global relevance flagged;# | AK29: Resource/capacity constraints;#Adoption & change resistance;# | AL29: Chris noted that only a small share of projects get digital support early enough, with most projects either not engaging the digital team or doing so too late. | AN29: Existing standards register_RTR Master.xlsx | AO29: Existing practice register | AP29: Imported | AS29: Not reviewed | AW29: Existing practice
A30: ESP-S025 | B30: ESP-P025 | C30: Governance | E30: Digital fit assessment (UK&I) | F30: UK&I;# | G30: UK&I | H30: UK&I projects around DG3 assessment | I30: Low | J30: Low | K30: Clear | L30: Medium | M30: High | N30: Norway, UK&I, Denmark | P30: 3 | Q30: Project startup is unclear/slow;#Inconsistent use of standards/templates;# | R30: Projects start with avoidable digital risks when complexity, CDE needs, standards gaps and BEP requirements are not assessed early. | S30: It is used to decide whether a project should be in a managed environment and to identify missing standards, BEP content, and delivery risks before mobilisation. | T30: Faster / clearer project startup;#Better compliance / consistency;#Improved transparency for PMs / teams;# | U30: The assessment gives a structured way to understand whether digital support and a managed CDE are needed rather than relying on ad hoc judgement. | V30: Used in a small minority of relevant projects;# | W30: This was described as new rather than fully established. | X30: Developing;# | Y30: Helen said the digital fit assessment has just come in and they have not yet seen the benefits. | Z30: Clear and role-based;# | AA30: The digital fit assessment is completed by the digital delivery managers around DG3. | AB30: Clearly worth deeper analysis;# | AC30: Promising standard decision tool with clear reuse potential, but still too new to call proven in UK&I. | AD30: Process/way of working;#Templates/standards;# | AE30: Digital fit assessment | AF30: Assessment completed around DG3 to understand project complexity, digital context, goals, gaps, and whether the project needs a managed CDE and stronger digital delivery support. | AG30: Specific project types;# | AH30: Early phase planning and design | AI30: Miro specifically flagged the digital fit assessment as scalable globally, but Helen said benefits have not yet really been seen because it has only just been introduced. | AJ30: Global relevance flagged;# | AK30: Adoption & change resistance;#Governance/ownership unclear;# | AL30: The workshop noted that some projects still start in the wrong system because engagement happens late or the assessment is not applied early enough. | AN30: Existing standards register_RTR Master.xlsx | AO30: Existing practice register | AP30: Imported | AS30: Not reviewed | AW30: Existing practice
A31: ESP-S026 | B31: ESP-P026 | C31: Production Environments & Configurations | E31: ISO 19650-aligned ProjectWise deployment model (UK&I) | F31: UK&I;# | G31: UK&I | H31: UK&I major transport projects using ProjectWise | I31: Medium | J31: High | K31: Clear | L31: High | M31: High | N31: Norway, UK&I, Denmark, Major Projects | P31: 4 | Q31: Inconsistent use of standards/templates;#External collaboration friction;#Poor onboarding of new team members;# | R31: Users and partners struggle across major projects when CDE structures, workflows, metadata, security and ISO 19650 practices are not standardised. | S31: The standardised build gives users a familiar environment across projects and supports controlled collaboration, revision, review and issue of deliverables. | T31: Better compliance / consistency;#Easier collaboration externally;#Faster / clearer project startup;# | U31: Peter described the standard build as a major reason some projects can be deployed very quickly, with common structures also supporting automation and reporting. | V31: Used in some relevant projects;# | W31: Chris said only the largest UK projects are typically the ones on ProjectWise. | X31: Operational;# | Y31: The deployment model is standardised around ISO 19650, with templated groups, folders, workflows, and staging checks. | Z31: Clear and role-based;# | AA31: Deployment is a collaborative effort between the ProjectWise admin team, BIM manager/BIM lead and digital leads; Peter Wilman presented as the UK Transport ProjectWise Lead. | AB31: Clearly worth deeper analysis;# | AC31: Mature operational model with strong practical value, especially where ISO-style control and multi-organisation collaboration are needed. | AD31: Platform setup (CDE, hub, workspace);#Templates/standards;#Process/way of working;# | AE31: ProjectWise, Civil 3D, ISO 19650 | AF31: UK&I major projects commonly use a managed ProjectWise deployment aligned to ISO 19650, with standard folder structures, workflows, metadata, granular security and support for internal, external and client users. | AG31: Specific project types;# | AH31: Major transport projects | AI31: Miro highlighted broader global relevance around adapting to ISO 19650 and using clearer standards to determine which CDE should be used. | AJ31: Global relevance flagged;# | AK31: Tool/platform dependencies;#Local regulations/client constraints;# | AL31: The model is closely tied to ProjectWise and UK compliance requirements, including cases where data must remain UK-based. | AN31: Existing standards register_RTR Master.xlsx | AO31: Existing practice register | AP31: Imported | AS31: Not reviewed | AW31: Existing practice
A32: ESP-S027 | B32: ESP-P027 | C32: Production Environments & Configurations | E32: ProjectWise build sheet and staged mobilisation checks (UK&I) | F32: UK&I;# | G32: UK&I | H32: UK&I major transport ProjectWise deployments | I32: Low | J32: Medium | K32: Clear | L32: Low | M32: High | N32: UK&I | P32: 1 | Q32: Project startup is unclear/slow;#Inconsistent use of standards/templates;# | R32: ProjectWise deployments are more error-prone when CDE requirements are not captured, staged, checked and approved before the environment goes live. | S32: This creates a repeatable deployment method and reduces the risk of configuration mistakes before users start working live in production. | T32: Faster / clearer project startup;#Better compliance / consistency;# | U32: The UK&I team described this as one reason a standard project can sometimes be built and made live within a couple of hours. | V32: Used in many relevant projects;# | W32: Presented as part of the standard ProjectWise deployment process for major UK projects. | X32: Operational;# | Y32: The build sheet and staged mobilisation checks are part of the current ProjectWise deployment process. | Z32: Exists but person dependent;# | AA32: The ProjectWise admin team builds the environment, while the BIM manager or BIM lead carries out the mobilisation checks before production. | AB32: Clearly worth deeper analysis;# | AC32: Very practical deployment method with visible reuse potential, particularly for countries wanting a faster standard startup process. | AD32: Process/way of working;#Templates/standards;#Automation/dashboard;# | AE32: Excel build sheet, PowerShell, ProjectWise staging data source | AF32: Requirements are captured in an Excel build sheet, then the environment is built first in a staging data source, checked by the BIM lead for workflows, numbering and environments, and only then promoted into production. | AG32: Specific project types;# | AH32: Major transport projects using ProjectWise | AI32: Miro specifically called out the build sheet as something Finland could potentially adapt, suggesting wider value if formalised further. | AJ32: Flagged for specific countries;# | AK32: Resource/capacity constraints;#Governance/ownership unclear;# | AL32: It works well but still depends on experienced admins and has not yet been fully formalised into a broader self-service or enterprise process. | AN32: Existing standards register_RTR Master.xlsx | AO32: Existing practice register | AP32: Imported | AS32: Not reviewed | AW32: Existing practice
A33: ESP-S028 | B33: ESP-P028 | C33: Project Setup & Coordination | E33: ProjectWise dashboards and Teams reporting (UK&I) | F33: UK&I;# | G33: UK&I | H33: UK&I projects using ProjectWise platforms | I33: Low | J33: Low | K33: Clear | L33: Low | M33: High | P33: 0 | Q33: Poor onboarding of new team members;#Project startup is unclear/slow;#Inconsistent use of standards/templates;# | R33: Project managers and Digital Delivery Managers lack early warning of access, workflow and activity issues when ProjectWise data is not easily visible (e.g. in dashboards.) | S33: The dashboards make audit trail, access, workflow and activity information more visible to project managers and Digital Delivery Managers, and help teams spot issues early. | T33: Improved transparency for PMs / teams;#Better compliance / consistency;#Faster / clearer project startup;# | U33: Examples included daily digests in Teams, user dashboards, file activity views and reports used to challenge oversized models and other delivery issues. | V33: Used in many relevant projects;# | W33: Peter described daily Teams digests and existing dashboards in ProjectWise projects, while more advanced dashboards are still being developed. | X33: Developing;# | Y33: Dashboards are already in use, but the transcript says they are still being expanded and are linked to named individuals, so the approach appears useful but not yet fully mature. | Z33: Exists but person dependent;# | AA33: The dashboards are being set up by Paul Duffy in the UK, with Peter presenting them from the ProjectWise admin side. | AB33: Clearly worth deeper analysis;# | AC33: One of the clearest UK&I reuse candidates because it turns hidden system data into visible operational insight for projects. | AD33: Automation/dashboard;#Process/way of working;# | AE33: Teams, ProjectWise web services gateway, dashboards, AI-enabled queries | AF33: UK&I exposes ProjectWise data through dashboards surfaced in Teams, covering user management, activity, workflow status, licence status, project-specific metrics and newer AI-style query views. | AG33: Specific project types;# | AH33: Projects using ProjectWise | AI33: Miro explicitly highlighted user-management dashboards, ProjectWise advanced dashboards and the general idea of bringing data and insights to project users as scalable. | AJ33: Global relevance flagged;# | AK33: Resource/capacity constraints;#Adoption & change resistance;# | AL33: The capability appears valuable but depends on continued development time, user engagement and a clear understanding of which insights projects actually need. | AN33: Existing standards register_RTR Master.xlsx | AO33: Existing practice register | AP33: Imported | AS33: Not reviewed | AW33: Existing practice
A34: ESP-S029 | B34: ESP-P029 | C34: Project Setup & Coordination | E34: External user and licence request workflow (UK&I) | F34: UK&I;# | G34: UK&I | H34: UK&I externally collaborative ProjectWise projects | I34: Medium | J34: Medium | K34: Clear | L34: Low | M34: High | P34: 0 | Q34: External collaboration friction;#Poor onboarding of new team members;#Project startup is unclear/slow;# | R34: External collaborators are delayed when user creation, licence assignment and licence expiry monitoring are handled through repeated manual requests. | S34: The workflow replaces repeated service requests and reduces delays for externals who need ProjectWise access and licences to participate in delivery. | T34: Easier collaboration externally;#Improved transparency for PMs / teams;#Faster / clearer project startup;# | U34: The UK&I team described this as a practical improvement because external users had previously been blocked when licences expired without warning. | V34: Used in many relevant projects;# | W34: Presented as part of the ProjectWise user-management process, especially where external users need access and licences. | X34: Operational;# | Y34: External user requests and licence assignment are already handled through the dashboard and admin workflow. | Z34: Exists but person dependent;# | AA34: BIM managers request external users, and the admin team creates the users and assigns licences through the workflow. | AB34: Potential, but needs clarification;# | AC34: Useful support pattern with good operational value, though narrower in scope than the broader deployment and dashboard models. | AD34: Automation/dashboard;#Process/way of working;# | AE34: Forms, dashboards, ProjectWise user management, licence tracking | AF34: BIM managers can request external users through a dashboard-driven process, with automatic user creation steps, licence assignment, and monitoring of upcoming licence expiry so access issues are handled more proactively. | AG34: Specific project types;# | AH34: Projects using ProjectWise; externally collaborative projects | AI34: Miro references to UK&I licence issuing and user-management dashboards suggest wider reuse potential, especially where external collaborators are common. | AJ34: Global relevance flagged;# | AK34: Tool/platform dependencies;#Resource/capacity constraints;# | AL34: The workflow depends on the surrounding ProjectWise admin model and ongoing monitoring of licences, users and dashboard processes. | AN34: Existing standards register_RTR Master.xlsx | AO34: Existing practice register | AP34: Imported | AS34: Not reviewed | AW34: Existing practice
A35: ESP-S030 | B35: ESP-P030 | C35: Production Environments & Configurations | E35: SPOT Workflow (Major Projects) | F35: MajorProjects#;CivilStructures;#Finland;#Norway;#Denmark | G35: DK, NO, FI, UK&I | H35: Major Projects: bridges, Finland/Denmark/UK/Norway, 10+ projects | I35: Low | J35: Low | K35: Partly clear | L35: Medium | M35: High | N35: UK&I, Denmark, Major Projects | O35: Major Projects | P35: 4 | R35: Projects waste time and introduce errors when core design data is duplicated across tools instead of managed through a shared data backbone. | S35: Centralizes project data to reduce manual data handling, errors, and rework Enables parallel, multi-tool workflows (BIM, FEM, scripting) with a single data backbone Improves data consistency and reuse across projects | T35: Time savings (observed 25–30% in comparable projects in ROI section; general ROI targets 90–230% in Year 1); reduces data duplication/outdated information; faster onboarding | V35: 10+ projects, 20+ structures; regions: Finland, Denmark, UK, Norway | W35: Security, access, and support risks currently noted; 5–10 simultaneous projects discussed as risk if Phase-2 not implemented | X35: MVP transitioning to Beta/Phase-2; planning for scale and documentation | Y35: Requires platform hardening, documentation, scalability, tool integration, training | Z35: Product Owner listed as Augustin Ceillier (Phase-2); team includes Anjani K V S N and Rafal | AB35: Phase-2 is to enable multi-project adoption; risks if not implemented (cross-project breakage, increased support risk) | AD35: Central SPOT database (KENNEL) plus project SPOT instances Building blocks, JSON data model, templates, and workflows Data flow between SPOT, PILARI, and connected tools | AE35: Excel, JSON, Grasshopper/SOFISTIK environments Toolkits for Python, GH, and more (tool integration) | AF35: Architecture includes data modeling, QA, and cross-project scalability In which projects: Crown Bridge, Kirjala Bridge (examples cited); E18/E39, Olufusarbru, and others; multiple bridges across Finland, Denmark, UK, Norway | AG35: Crown Bridge, Kirjala Bridge; E18/E39, Olufusarbru, and others; multiple bridges across Finland, Denmark, UK, Norway | AI35: 5–10 parallel projects requires robust hosting, audit, and governance Standardized building blocks and automated validation essential | AJ35: Global relevance flagged;# | AK35: Security/access hosting risks; reliance on key individuals; risk of cross-project changes; need for audit and standardization | AN35: Existing standards register_RTR Master.xlsx | AO35: Existing practice register | AP35: Imported | AS35: Not reviewed | AW35: Existing practice
A36: ESP-S031 | B36: ESP-P031 | C36: Production Environments & Configurations | D36: Augustin Ceillier; Tung Quach Thanh; Sean LeCoultre; Stephen Roberts | E36: CODA Data Dictionary (CDD) (Major Projects) | F36: MajorProjects;#CivilStructures;#Finland | G36: NO, FI | H36: Major Projects: E18/E39, bridges, civil structures | I36: Low | J36: Low | K36: Partly clear | L36: Low | M36: High | N36: Major Projects | P36: 1 | R36: Automation and data reuse break down when attributes, definitions and allowed values differ by project, tool or individual script. | S36: Ensures all project teams follow the same attribute template; provides a single source of truth for attributes, definitions, types and allowed values; eliminates spelling/syntax variations that break scripts; enables data reusability across projects | T36: Centralised reference of attributes preventing script crashes from spelling mistakes; makes learnings from past projects accessible; consistency across projects using CODA tools; streamlined reuse of archived material; prevents duplicating content with each new tool | V36: Active on E18/E39 Gartnerløkka–Kolsdalen (15 bridges, 5 culverts, 34 retaining walls, noise barriers, temporary structures); referenced in Crown Bridge, Olfusa projecct, FSQ project | X36: In development | AA36: Will require an ADD team for ongoing maintenance and derogations procedure | AB36: Scalable but requires ongoing monitoring and maintenance; needs input from wider industry team members; centrally maintained model expected to scale across projects using CODA toolset | AC36: Mapped against bSDD and IFC4.3 to support interoperability and scaling | AD36: Centralized reference of attributes, definitions, types and allowed values, structured as: Asset List, Discipline & System assets, Component Catalogue, Attribute Definitions | AE36: Excel-based dictionary | AG36: E18/E39 Gartnerløkka–Kolsdalen; Crown Bridge (PoC); E45 Overpasses; Ölfusárbrú; Kulosaarensilta | AI36: Assumes central maintenance, a derogations procedure for new content, few fed by the many approach where project teams contribute missing content; reuse across CODA-aligned projects | AJ36: Bridge design projects; other civil structures and disciplines (extension envisaged); model-driven / drawingless delivery environments | AK36: Requires ongoing monitoring & maintenance; needs cross-discipline input to develop content; risk of holding up project delivery if derogation process not efficient; dependency on bSDD/IFC alignment; high variation in attribute syntax across scripts/projects to be normalised | AL36: Needs the data strategy and data structure established to work properly (flagged as prerequisite for several CODA features such as Asset Data Delivery Workflow, Master CODA CDD, Project DB authentication) | AN36: Existing standards register_RTR Master.xlsx | AO36: Existing practice register | AP36: Imported | AS36: Not reviewed | AW36: Existing practice
A37: ESP-S032 | B37: ESP-P032 | C37: Production Environments & Configurations | E37: BSDD testing / mapping (Major Projects) | F37: MajorProjects;#CivilStructures;#Finland | G37: FI | H37: Major Projects civil structures, pilot phase | I37: NA | J37: Low | K37: Unclear | L37: Low | M37: Low | N37: Finland, Major Projects | O37: Finland, Major Projects | P37: 4 | R37: Interoperability remains difficult when project data dictionaries are not mapped to recognised industry standards such as bSDD and IFC 4.3. | S37: Aims to align CODA Data Dictionary (CDD) content with an industry-standard data dictionary (bSDD) and IFC 4.3 to support interoperability and standardised data exchange | T37: Not quantified in context. Implied value: interoperability with industry standards, reuse of standardised classifications, alignment with IFC 4.3 | X37: Not started | AD37: Mapping exercise between the CODA Data Dictionary (CDD) content and the buildingSMART Data Dictionary (bSDD); review of compatibility with IFC 4.3 | AE37: buildingSMART Data Dictionary (bSDD); IFC 4.3; CODA Data Dictionary (CDD) | AN37: Existing standards register_RTR Master.xlsx | AO37: Existing practice register | AP37: Imported | AS37: Not reviewed | AW37: Existing practice
A38: ESP-S033 | C38: Digital Project Roles | D38: Eirik Storaas Kristoffersen / Diana Soots | E38: Ramboll role standard, Digital Delivery Manager and the digital project roles | F38: Group | G38: All | I38: Low | J38: Medium | K38: Partly clear | L38: High | M38: High

Sheet Initiatives
A1: Knwon ongoing Ramboll initiatives
A2: One row per initiative. Evidence-based owner, unit, status, and date remain blank unless explicitly supported by a source.
A5: InitiativeID | B5: InitiativeName | C5: InitiativeDescription | D5: Status | E5: Next steps | F5: OwnerAsEvidenced | G5: SponsoringUnitAsEvidenced | H5: StatusAsEvidenced | I5: NormalizedStatus | J5: EvidenceSummary | K5: EvidenceDate | L5: VerificationNeeded | M5: SourceReference | N5: ReviewStatus | O5: Reviewer | P5: ReviewerComments | Q5: ReviewDecisionID
A6: PI-RTR-001 | B6: RTR Software Standardisation Exercise | C6: Transport-wide exercise to map engineering software by service line/spearhead, identify overlaps, improve interoperability and establish an evidence-based basis for possible standardisation and rationalisation. | F6: Anne-Sophie Omel, Portfolio Lead in Transport IDT | H6: Actions and next steps are defined: appoint representatives, analyse the landscape, conclude after 1–2 months and prepare a decommissioning plan. | I6: Planned | J6: The source defines a Transport engineering-software standardisation exercise, its objectives, principles, country-analysis actions and planned conclusion/decommissioning steps. | K6: 46252 | L6: Yes | M6: RTR Software Standardisation Exercise.pptx — https://ramboll.sharepoint.com/sites/DITransportMarket-XXXXIDTLeadershipTeam/_layouts/15/Doc.aspx?sourcedoc=%7B3027A090-10BA-4663-8454-1599D13A753F%7D&file=RTR%20Software%20Standardisation%20Exercise.pptx&action=edit&mobileredirect=true&DefaultItemOpen=1 | N6: Approved | O6: Eirik Storaas Kristoffersen | P6: Reviewed by Eirik Storaas Kristoffersen and retained in the initiative register. | Q6: RD-001
A7: PI-RTR-002 | B7: Unified Production Environment (UPE) | C7: Global initiative to align supported production platforms, interoperability, data governance, production knowledge and streamlined project environments, with AI and data-centric delivery as target outcomes. | F7: David Thomson — Product Owner | H7: UPE is in the exploration phase, with ongoing contributing work and an explicit list of active and planned initiatives. | I7: Active | J7: The source identifies UPE as an initiative, places it in exploration with ongoing work, describes production-platform/data/process scope, and lists active and planned components. | K7: 46251 | L7: Yes | M7: Unified Production Environment - Steer Co#1 Setting the scene for the way forward.pptx — https://ramboll-my.sharepoint.com/personal/david_thomson_ramboll_com/_layouts/15/Doc.aspx?sourcedoc=%7B605CB1B1-B756-4011-B161-643146F3CA97%7D&file=Unified%20Production%20Environment%20-%20Steer%20Co%231%20Setting%20the%20scene%20for%20the%20way%20forward.pptx&action=edit&mobileredirect=true&DefaultItemOpen=1 | N7: Approved | O7: Eirik Storaas Kristoffersen | P7: Reviewed by Eirik Storaas Kristoffersen and retained in the initiative register. | Q7: RD-002
A8: PI-RTR-002-01 | B8: UPE - Production Process & Knowledge | C8: Establish a trusted UPE Production Process & Knowledge foundation that structures the roles, processes, standards and templates needed to execute projects, and captures, governs and connects knowledge generated through delivery. Today knowledge from 30,000+ projects is fragmented across tools and individual experience, causing time lost finding or recreating ways of working, inconsistent quality and person-dependent delivery. The foundation enables reuse, continuous improvement, global ways of working and AI-ready knowledge; it does not replace Camino, implement the Project Delivery Model in the business, or build an end-to-end process or full AI layer. | D8: GBA requirements have been collected and validation with the GBAs is starting; the problem statement is validated, while the requirement set is not yet finally endorsed. | E8: Validate the shared, single-GBA and potential requirements with GBA HoDD&P stakeholders; confirm cross-GBA applicability, security and confidentiality boundaries, and ownership. Prioritise initial high-impact production processes, define knowledge governance and review cadence, then progress UPE discovery and pilots (POVs). | G8: DD&P Division | H8: Validated problem statement (slide 3); GBA requirements collected in shared, single-GBA and potential groups (slides 4, 12–13), with initial GBA input requested by 8 October 2026. Validation with GBAs is starting. | I8: Active | J8: Slide 3 describes fragmented production knowledge and the proposed governed UPE foundation, names Diana Soots as Exploration Lead, and leaves requestor, sponsor and Product Owner TBD. Slides 2, 4, 12 and 13 distinguish requirements captured for GBA input from final validation; current validation phase also confirmed by the initiative request. | K8: 46302 | L8: Yes | M8: 2026_09_28 - UPE Production Process & Knowledge global requirements.pptx, slides 2–4, 12–13; phase update supplied by Eirik Storaas Kristoffersen, 8 Oct 2026 | N8: Not reviewed
A9: PI-RTR-003 | B9: Transforming Document Management | C9: Global project redesigning document-management processes and preparing migration and integrations for a new document management system, with behavioural change and adoption across Ramboll projects. | D9: Process redesign and migration/integration preparation are under way. The high-level target is transition to the new document management system in the second half of 2027; the detailed migration and user-transition timetable is not yet established. | E9: Define information architecture, metadata, lifecycle and governance, quality assurance, access, standardisation, naming conventions and possible AI use; map migration sources and decide what should migrate; validate and prepare 4,970 projects; plan integrations with Microsoft 365/SharePoint, Maconomy, CRM, the PI Tool and key CDE platforms; involve Transport delivery and information-management experts; establish the detailed H2 2027 migration and user-transition timetable. Initial launch migration scope is Filery and CRM SharePoint; other sources such as Project Portal may require a later project. | F9: Morten Hansen — Project Owner | H9: The project is moving into process redesign alongside migration and integration preparation. The high-level plan is to transition to a new document management system in H2 2027, but the detailed migration and user-transition timetable is not yet established. Initial launch migration scope is Filery and CRM SharePoint; other sources may follow separately. | I9: Active | J9: The 18 September Transport update records active process redesign and migration/integration preparation, informed by pain-point workshops with 14 Transport participants. It identifies an H2 2027 target, an initial Filery and CRM SharePoint migration scope, 4,970 projects requiring review, planned enterprise/CDE integrations, and the need for Transport subject-matter-expert involvement. | K9: 46283 | L9: Yes | M9: Introduction to Transforming Document Management project.pptx — https://ramboll.sharepoint.com/sites/InformationabouttheInsightsintoDMSproject/_layouts/15/Doc.aspx?sourcedoc=%7B2C45230D-6298-4E39-B5B2-486433737999%7D&file=Introduction%20to%20Transforming%20Document%20Management%20project.pptx&action=edit&mobileredirect=true&DefaultItemOpen=1; Transforming Document Management: status and next steps for Transport — email from Eirik Storaas Kristoffersen, 18 September 2026; TDM status 11.09.2026.pptx — https://ramboll-my.sharepoint.com/:p:/g/personal/jped_ramboll_dk/IQBrjFCJHe3JQY98boBWikRVAfK-9EiWvg8Crp8H-gyVNqY?e=DeJ3fS | N9: Not reviewed | P9: Updated from the 18 September 2026 Transport status email; requires review of the revised status, scope and next steps.
A10: PI-RTR-004 | B10: Enabling Citizen Development | C10: Ramboll Tech DD&P discovery and pilot initiative to determine business needs, tooling, enablement, governance and safe ways for colleagues to create lightweight automation and solutions. | H10: DD&P stated that it wanted to “get moving”; the first step was a survey/discovery exercise followed by proposed focused pilots. A later UPE status records the Citizen Developer Toolkit POD as activated. | I10: Active | J10: The email explicitly establishes Citizen Development work within DD&P and a survey/discovery-to-pilot approach; the UPE status later states that a Citizen Developer Toolkit POD was activated. | K10: 46133 | L10: Yes | M10: Starting work on Citizen Development in DD&P — Outlook item AAMkADFkNTVkNTdkLTQ2NzktNGUwMy04ZjUwLWJjOGU5NWVmZmVlOABGAAAAAAAwqbqR6chTRqrGrbICvYZiBwAmAYPWE1oSQJIchgDHMYYlAAAFjIT4AAAGgHAtU47mQbWmGDo%2bojP%2bAAfqK8P6AAA%3d; supporting source: Unified Production Environment - Steer Co#1 Setting the scene for the way forward.pptx — https://ramboll-my.sharepoint.com/personal/david_thomson_ramboll_com/_layouts/15/Doc.aspx?sourcedoc=%7B605CB1B1-B756-4011-B161-643146F3CA97%7D&file=Unified%20Production%20Environment%20-%20Steer%20Co%231%20Setting%20the%20scene%20for%20the%20way%20forward.pptx&action=edit&mobileredirect=true&DefaultItemOpen=1 | N10: Approved | O10: Eirik Storaas Kristoffersen | P10: Reviewed by Eirik Storaas Kristoffersen and retained in the initiative register. | Q10: RD-004
A11: PI-RTR-005 | B11: Script Sharing Platform rollout and scaling | C11: Scale a live, governed environment for sharing and reusing engineering automation assets including scripts, plugins and visual-programming solutions. | F11: Simon Scott Siedler — Product Owner | H11: The platform is live; development and UI improvements were complete, Transport and Buildings feedback had been incorporated, and it was ready for broader adoption and scaling. | I11: Active | J11: Internal sources identify the platform, its Product Owner, completed development/UAT improvements and the next scaling/adoption phase. | K11: 46245 | L11: Yes | M11: Re: Can you point us in the right direction? — Outlook item AAMkADFkNTVkNTdkLTQ2NzktNGUwMy04ZjUwLWJjOGU5NWVmZmVlOABGAAAAAAAwqbqR6chTRqrGrbICvYZiBwAmAYPWE1oSQJIchgDHMYYlAAAFjIT4AAAGgHAtU47mQbWmGDo%2bojP%2bAAmqCfmGAAA%3d; Re: Topic for discussion & my recommendation: Proceed with Meerkat Town and Script Sharing Platform rollout — Outlook item AAMkADFkNTVkNTdkLTQ2NzktNGUwMy04ZjUwLWJjOGU5NWVmZmVlOABGAAAAAAAwqbqR6chTRqrGrbICvYZiBwAmAYPWE1oSQJIchgDHMYYlAAAFjIT4AAAGgHAtU47mQbWmGDo%2bojP%2bAAozvRC3AAA%3d | N11: Approved | O11: Eirik Storaas Kristoffersen | P11: Reviewed by Eirik Storaas Kristoffersen and retained in the initiative register. | Q11: RD-005
A12: PI-RTR-006 | B12: Software processes & portal | C12: Ramboll Tech workstream improving software-portfolio governance, employee software journeys, request workflows and production-software support flows. | H12: “Stage 4 — execution started”; solutions were defined and work was underway across governance, employee journeys, requests and production support. | I12: Active | J12: The Tech Task Force update explicitly identifies the workstream, states that execution had started and enumerates the four improvement areas underway. | K12: 46155 | L12: Yes | M12: FW: Tech task force: update for Tech LT — Outlook item AAMkADFkNTVkNTdkLTQ2NzktNGUwMy04ZjUwLWJjOGU5NWVmZmVlOABGAAAAAAAwqbqR6chTRqrGrbICvYZiBwAmAYPWE1oSQJIchgDHMYYlAAAFjIT6AAAGgHAtU47mQbWmGDo%2bojP%2bAAUPEC%2bEAAA%3d; Software Management Processes and Portal Overview.pptx — https://ramboll.sharepoint.com/sites/BoostingTechProfitability/_layouts/15/Doc.aspx?sourcedoc=%7B7684EA9F-9243-4274-BB43-0AF9E0008607%7D&file=Software%20Management%20Processes%20and%20Portal%20Overview.pptx&action=edit&mobileredirect=true&DefaultItemOpen=1 | N12: Approved | O12: Eirik Storaas Kristoffersen | P12: Reviewed by Eirik Storaas Kristoffersen and retained in the initiative register. | Q12: RD-006
A13: PI-RTR-007 | B13: Building our Project Management and Delivery department within Major Projects | C13: Transport Major Projects initiative to build geographically distributed PMD capability supporting more reliable and harmonised delivery of large infrastructure projects. | G13: Major Projects | H13: PMD departments were being opened across geographies, recruitment was continuing, and second-half work would focus on delivery and the second Major Projects Handbook edition. | I13: Active | J13: Major Projects explicitly records its decision to build the PMD department, current geographic expansion and continuing delivery/handbook work. | K13: 46244 | L13: Yes | M13: Viva Engage: Building our Project Management and Delivery department within Major Projects — https://engage.cloud.microsoft/main/threads/eyJfdHlwZSI6IlRocmVhZCIsImlkIjoiMzk4MjQ1MjcxMjA1NDc4NCJ9 | N13: Approved | O13: Eirik Storaas Kristoffersen | P13: Reviewed by Eirik Storaas Kristoffersen and retained in the initiative register. | Q13: RD-008
A14: PI-RTR-009 | B14: The Enhanced Delivery Ecosystem | C14: Buildings initiative connecting project and enterprise data with production knowledge and AI-enabled design and delivery. InsightHub is described as Ramboll’s data platform that unlocks business-unit data for use by other tools, including through a data explorer and REST API. Knowledge Management is described as a curated knowledge database of standards, guides, quality-assurance checklists, and design rules, supported by the Global Technical Networks, with a proposed Knowledge Assistant for retrieving information from existing knowledge libraries. The wider ecosystem also includes agentic design and delivery, citizen development, and Buildings Catalyst Teams working to prove and scale new ways of working. | G14: Buildings | J14: The Buildings presentation describes The Enhanced Delivery Ecosystem as a connected ecosystem in which past and current project and enterprise data flows through Ramboll systems, is made available through InsightHub, curated into production knowledge, and used by engineers, AI agents, and computational designers in project delivery. InsightHub is described as Ramboll’s data platform that unlocks RBU data and provides a foundation on which other tools can build. The presentation references an InsightHub data explorer and REST API as parts of this data-platform component. Knowledge Management is described as a curated knowledge database containing standards, guides, quality-assurance checklists, and design rules, supported by the Global Technical Networks. The wider Knowledge Management vision connects knowledge and learning held across Ramboll Academy, online learning platforms, SharePoint, Microsoft Teams, and Viva Engage through search and governance. The stated challenges include knowledge silos, outdated content, lack of a single source, findability, and ownership. A proposed Knowledge Assistant is intended to answer content-specific questions using information sourced from existing knowledge libraries. Supporting meeting evidence states that Buildings currently uses SharePoint-based eTools as a governed repository for templates, standards, and processes, with an AI search layer added to improve retrieval. The same meeting evidence states that wider cross-GBA work is mapping existing knowledge-management initiatives, technologies, goals, use cases, and requirements before deciding whether a global or enterprise-level solution is required. The wider Enhanced Delivery Ecosystem also includes agentic design and delivery, citizen development, and Buildings Catalyst Teams working across the ecosystem to prove and scale new ways of working. | K14: 46267 | L14: Yes | M14: 260825 Buildings SE Leadership AI Day - Copy.pptx — 260825 Buildings SE Leadership AI Day - Copy.pptx supporting evidence: UPE - production process and knowledge bi-weekly check in, 27 August 2026 | N14: Approved | O14: Eirik Storaas Kristoffersen

Sheet VIEW_WS1_Related work
A1: Workshop 1 problems and related existing work | B1: Live view of selected fields from WS1_Problems. Edit source records in WS1_Problems, not in this view.
A4: Problem ID | B4: Short title | C4: Relevant ongoing initiatives | D4: Relevant existing standards and practices
A5: ='Q3_Top problems'!A11 -> WS1-P013 | B5: ='Q3_Top problems'!D11 -> Scattered guidance and support information | C5: ='Q3_Top problems'!L11 -> PI-RTR-002 Unified Production Environment: Production knowledge is part of its scope and could make guidance more consistent, although a single entry point for all support, education, and onboarding information is not explicitly evidenced. PI-RTR-003 Transforming Document Management: A fit-for-purpose document-management system and revised processes can improve the organisation of document-management guidance, but not all software, education, and working-method information. PI-RTR-006 Software processes & portal: Directly addresses employee software journeys, software requests, and production-software support flows, responding to scattered software guidance and support information. | D5: ='Q3_Top problems'!M11 -> ESP-S002 ProjectWise manager guide and standards portal (Denmark) ESP-S005 CAD project manual and transport standards portal (Denmark) ESP-S006 Teams-based product information and support channel (Denmark) ESP-S011 Transport software standards portal and Teams communication channels (Finland) ESP-S012 Super-user network and office roadshow support model (Finland) ESP-S017 Project SharePoint/Teams information hub (Norway) ESP-S023 Project Hub (SharePoint coordination layer) (Sweden)
A6: ='Q3_Top problems'!A12 -> WS1-P008 | B6: ='Q3_Top problems'!D12 -> Digital risks identified too late | C6: ='Q3_Top problems'!L12 -> N/A | D6: ='Q3_Top problems'!M12 -> ESP-S024 Early-phase digital delivery manager involvement (UK&I) ESP-S025 Digital fit assessment (UK&I)
A7: ='Q3_Top problems'!A13 -> WS1-P027 | B7: ='Q3_Top problems'!D13 -> Consistency across departments in terms of digital plan and focus, lack of HoD KPI's supporting improvements in the digital space | C7: ='Q3_Top problems'!L13 -> PI-RTR-007 Building our Project Management and Delivery department within Major Projects: Its department-building, geographic expansion, delivery focus, and Major Projects Handbook can provide stronger common direction within Major Projects, but do not evidence aligned priorities and performance measures across all Transport departments. | D7: ='Q3_Top problems'!M13 -> N/A
A8: ='Q3_Top problems'!A14 -> WS1-P018 | B8: ='Q3_Top problems'!D14 -> Project standards not fully implemented | C8: ='Q3_Top problems'!L14 -> PI-RTR-001 RTR Software Standardisation Exercise: Can support consistent software choices, but does not directly implement project models, folder structures, templates, or standards. PI-RTR-002 Unified Production Environment: Alignment of production processes, knowledge, platforms, and environments supports practical implementation of consistent project standards and ways of working. PI-RTR-003 Transforming Document Management: Process revision, system implementation, and behavioural adoption directly support implementation of document-management standards, although not all project-production standards. PI-RTR-007 Building our Project Management and Delivery department within Major Projects: The harmonised delivery focus and Major Projects Handbook can support implementation of common delivery practices, but the documented scope does not specifically cover digital models or folder standards. | D8: ='Q3_Top problems'!M14 -> ESP-S001 ProjectWise manager governance model (Denmark) ESP-S003 ProjectWise for production - RAMDK (Denmark) ESP-S004 Managed workspace in ProjectWise (Denmark) ESP-S005 CAD project manual and transport standards portal (Denmark) ESP-S008 Quadri / Trimble Connect project environment (Finland) ESP-S009 Finnish configuration packages for design tools (Finland) ESP-S010 Forma pilot with discipline templates (Finland) ESP-S011 Transport software standards portal and Teams communication channels (Finland) ESP-S012 Super-user network and office roadshow support model (Finland) ESP-S019 CAD Configuration / Configuration Switch (Sweden) ESP-S020 Metadata and Naming + Managed Workspaces (Sweden) ESP-S023 Project Hub (SharePoint coordination layer) (Sweden) ESP-S026 ISO 19650-aligned ProjectWise deployment model (UK&I) ESP-S027 ProjectWise build sheet and staged mobilisation checks (UK&I)
A9: ='Q3_Top problems'!A15 -> WS1-P020 | B9: ='Q3_Top problems'!D15 -> Limited cross-country innovation sharing | C9: ='Q3_Top problems'!L15 -> PI-RTR-002 Unified Production Environment: Shared production knowledge can improve cross-country exchange of methods and solutions, although dedicated innovation-sharing arenas and tender application are not explicit. PI-RTR-005 Script Sharing Platform rollout and scaling: Makes reusable engineering automation assets visible across teams and geographies, directly improving sharing of one important category of production innovation, although it does not cover all types of innovation or tender collaboration. | D9: ='Q3_Top problems'!M15 -> N/A
A10: ='Q3_Top problems'!A16 -> WS1-P004 | B10: ='Q3_Top problems'!D16 -> Confidentiality restricts work sharing with REC | C10: ='Q3_Top problems'!L16 -> N/A | D10: ='Q3_Top problems'!M16 -> N/A
A11: ='Q3_Top problems'!A17 -> WS1-P019 | B11: ='Q3_Top problems'!D17 -> Coordination challenges in multidisciplinary projects | C11: ='Q3_Top problems'!L17 -> PI-RTR-002 Unified Production Environment: Shared production platforms and environments can reduce digital coordination friction across disciplines and business units, although multidisciplinary management is broader than its technical scope. PI-RTR-007 Building our Project Management and Delivery department within Major Projects: Building geographically distributed project-management and delivery capability directly responds to coordination and harmonisation challenges in complex multidisciplinary projects. | D11: ='Q3_Top problems'!M17 -> ESP-S005 CAD project manual and transport standards portal (Denmark) ESP-S013 Integrated multi-platform project environment (Norway) ESP-S014 BIMbot model exchange and automation layer (Norway) ESP-S017 Project SharePoint/Teams information hub (Norway) ESP-S023 Project Hub (SharePoint coordination layer) (Sweden) ESP-S024 Early-phase digital delivery manager involvement (UK&I) ESP-S026 ISO 19650-aligned ProjectWise deployment model (UK&I)
A12: ='Q3_Top problems'!A18 -> WS1-P014 | B12: ='Q3_Top problems'!D18 -> Confusion from multiple project platforms | C12: ='Q3_Top problems'!L18 -> PI-RTR-001 RTR Software Standardisation Exercise: Identifying software overlaps and rationalisation opportunities can reduce platform proliferation, although it does not define a single project-platform model. PI-RTR-002 Unified Production Environment: Its objective of aligning supported production platforms and streamlining project environments directly responds to confusion created by multiple platforms. PI-RTR-003 Transforming Document Management: Establishing a fit-for-purpose document-management system can reduce ambiguity concerning document-management platforms, but not the wider project-platform landscape. PI-RTR-006 Software processes & portal: Better software-portfolio governance and employee software journeys can clarify which software and services should be used, although this is not full platform consolidation. | D12: ='Q3_Top problems'!M18 -> ESP-S013 Integrated multi-platform project environment (Norway) ESP-S017 Project SharePoint/Teams information hub (Norway) ESP-S023 Project Hub (SharePoint coordination layer) (Sweden) ESP-S024 Early-phase digital delivery manager involvement (UK&I) ESP-S025 Digital fit assessment (UK&I)
A13: ='Q3_Top problems'!A19 -> WS1-P015 | B13: ='Q3_Top problems'!D19 -> Inefficient file exchange between vendors | C13: ='Q3_Top problems'!L19 -> PI-RTR-001 RTR Software Standardisation Exercise: Improved interoperability and software standardisation can reduce cross-vendor exchange friction, but the initiative does not establish file-exchange agreements, native-file rules, or automated exchange processes. PI-RTR-002 Unified Production Environment: Interoperability and streamlined production environments directly respond to recurring exchange problems between vendor ecosystems, although detailed format and native-file rules remain necessary. PI-RTR-003 Transforming Document Management: Revised document-management processes can improve control of exchanged files and documents, but do not resolve full design-tool interoperability. | D13: ='Q3_Top problems'!M19 -> ESP-S013 Integrated multi-platform project environment (Norway) ESP-S014 BIMbot model exchange and automation layer (Norway)
A14: ='Q3_Top problems'!A20 -> WS1-P002 | B14: ='Q3_Top problems'!D20 -> Barriers to scaling internally developed tools | C14: ='Q3_Top problems'!L20 -> PI-RTR-004 Enabling Citizen Development: Its discovery, tooling, enablement, and pilot work can reduce barriers to developing supported internal solutions, although it does not evidence a complete publishing and product-management pathway. PI-RTR-005 Script Sharing Platform rollout and scaling: Directly provides a governed way to publish, discover, reuse, and scale internally developed scripts, plugins, and visual-programming solutions. PI-RTR-006 Software processes & portal: Improved software governance, employee journeys, and request workflows may support access to approved tooling, but only partly address publication and scaling of internally developed tools. | D14: ='Q3_Top problems'!M20 -> N/A
A15: ='Q3_Top problems'!A21 -> WS1-P016 | B15: ='Q3_Top problems'!D21 -> Misaligned setups across software vendors | C15: ='Q3_Top problems'!L21 -> PI-RTR-001 RTR Software Standardisation Exercise: Directly analyses software overlaps and interoperability as a basis for standardisation, responding to inconsistent and misaligned multi-vendor setups. PI-RTR-002 Unified Production Environment: Aligning supported production platforms and interoperability directly addresses standard setups that are not aligned between software vendors. | D15: ='Q3_Top problems'!M21 -> ESP-S004 Managed workspace in ProjectWise (Denmark) ESP-S009 Finnish configuration packages for design tools (Finland) ESP-S013 Integrated multi-platform project environment (Norway) ESP-S019 CAD Configuration / Configuration Switch (Sweden) ESP-S020 Metadata and Naming + Managed Workspaces (Sweden)
A16: ='Q3_Top problems'!A22 -> WS1-P006 | B16: ='Q3_Top problems'!D22 -> Inconsistent data setup across tools | C16: ='Q3_Top problems'!L22 -> PI-RTR-001 RTR Software Standardisation Exercise: Its analysis of software overlaps and interoperability can address part of the inconsistent cross-tool setup, but not the full requirement for dynamically controlled and synchronised project data. PI-RTR-002 Unified Production Environment: Directly targets supported production platforms, interoperability, and data governance, responding to inconsistent data setup across tools. | D16: ='Q3_Top problems'!M22 -> ESP-S014 BIMbot model exchange and automation layer (Norway) ESP-S018 Asset coding and IFC 4x3 delivery pattern (Norway) ESP-S030 SPOT Workflow (Major Projects) ESP-S031 CODA Data Dictionary (CDD) (Major Projects) ESP-S032 BSDD testing / mapping (Major Projects)
... A62: ='Q3_Top problems'!A68 -> 0 | B62: ='Q3_Top problems'!D68 -> 0 | C62: ='Q3_Top problems'!L68 -> 0 | D62: ='Q3_Top problems'!M68 -> 0

Sheet Transport-UPE Summary
A1: Transport Requirement ID | B1: Transport Cluster | C1: Transport Requirement / Pain Point | D1: Source Reference | E1: UPE Coverage | F1: UPE Module / Section | G1: How UPE Covers It | H1: Not Covered Out-of-the-Box / Customisation Needed
